{"contact_address": "5th Floor, Dean Park House, 8-10 Dean Park Crescent, Bournemouth, BH1 1HL, United Kingdom", "contact_email": "hello@contentignite.com", "version": 1, "sellers": [{"name": "dw.com", "seller_id": "17952", "seller_type": "PUBLISHER"}, {"name": "bbc.co.uk", "seller_id": "17951", "seller_type": "PUBLISHER"}, {"name": "klsy.dev", "seller_id": "17950", "seller_type": "PUBLISHER"}, {"name": "independent.co.uk", "seller_id": "17949", "seller_type": "PUBLISHER"}, {"name": "freeridegames.com", "seller_id": "17948", "seller_type": "PUBLISHER"}, {"name": "pcguide.com", "seller_id": "17947", "seller_type": "PUBLISHER"}, {"name": "playbill.com", "seller_id": "17946", "seller_type": "PUBLISHER"}, {"name": "23viral.com", "seller_id": "17945", "seller_type": "PUBLISHER"}, {"name": "panlasangpinoy.com", "seller_id": "17944", "seller_type": "PUBLISHER"}, {"name": "will-mixen.de", "seller_id": "17943", "seller_type": "PUBLISHER"}, {"name": "thetravelbreeze.com", "seller_id": "17942", "seller_type": "PUBLISHER"}, {"name": "ilustrado.cl", "seller_id": "17941", "seller_type": "PUBLISHER"}, {"name": "laprensa.com.ni", "seller_id": "17940", "seller_type": "PUBLISHER"}, {"name": "free-power-point-templates.com", "seller_id": "17939", "seller_type": "PUBLISHER"}, {"name": "slidehunter.com", "seller_id": "17938", "seller_type": "PUBLISHER"}, {"name": "kingdomstv.com", "seller_id": "17937", "seller_type": "PUBLISHER"}, {"name": "gamesradar.com", "seller_id": "17936", "seller_type": "PUBLISHER"}, {"name": "techradar.com", "seller_id": "17935", "seller_type": "PUBLISHER"}, {"name": "announcements.scotsman.com", "seller_id": "17934", "seller_type": "PUBLISHER"}, {"name": "autosport.com", "seller_id": "17933", "seller_type": "PUBLISHER"}, {"name": "autosport.com", "seller_id": "17932", "seller_type": "PUBLISHER"}, {"name": "autosport.com", "seller_id": "17931", "seller_type": "PUBLISHER"}, {"name": "motorsport.com", "seller_id": "17930", "seller_type": "PUBLISHER"}, {"name": "motorsport.com", "seller_id": "17929", "seller_type": "PUBLISHER"}, {"name": "motorsport.com", "seller_id": "17928", "seller_type": "PUBLISHER"}, {"name": "formula1.com", "seller_id": "17927", "seller_type": "PUBLISHER"}, {"name": "broadbandspeedtest.org.uk", "seller_id": "17926", "seller_type": "PUBLISHER"}, {"name": "rightmove.co.uk", "seller_id": "17925", "seller_type": "PUBLISHER"}, {"name": "cnet.com", "seller_id": "17924", "seller_type": "PUBLISHER"}, {"name": "time.com", "seller_id": "17923", "seller_type": "PUBLISHER"}, {"name": "vice.com", "seller_id": "17922", "seller_type": "PUBLISHER"}, {"name": "dexerto.com", "seller_id": "17921", "seller_type": "PUBLISHER"}, {"name": "planetf1.com", "seller_id": "17920", "seller_type": "PUBLISHER"}, {"name": "planetsport.com", "seller_id": "17919", "seller_type": "PUBLISHER"}, {"name": "90min.com", "seller_id": "17918", "seller_type": "PUBLISHER"}, {"name": "skysports.com", "seller_id": "17917", "seller_type": "PUBLISHER"}, {"name": "fandom.com", "seller_id": "17916", "seller_type": "PUBLISHER"}, {"name": "toolspart.com", "seller_id": "17915", "seller_type": "PUBLISHER"}, {"name": "motorsportmagazine.com", "seller_id": "17914", "seller_type": "PUBLISHER"}, {"name": "wepc.com", "seller_id": "17912", "seller_type": "PUBLISHER"}, {"name": "sport5.co.il", "seller_id": "17911", "seller_type": "PUBLISHER"}, {"name": "marineweather.net", "seller_id": "17910", "seller_type": "PUBLISHER"}, {"name": "visitbristol.co.uk", "seller_id": "17909", "seller_type": "PUBLISHER"}, {"name": "discoveryorkshirecoast.com", "seller_id": "17908", "seller_type": "PUBLISHER"}, {"name": "windsor.gov.uk", "seller_id": "17907", "seller_type": "PUBLISHER"}, {"name": "visitwiltshire.co.uk", "seller_id": "17906", "seller_type": "PUBLISHER"}, {"name": "visit-westonsupermare.com", "seller_id": "17905", "seller_type": "PUBLISHER"}, {"name": "enjoystaffordshire.com", "seller_id": "17904", "seller_type": "PUBLISHER"}, {"name": "visitsouthport.com", "seller_id": "17903", "seller_type": "PUBLISHER"}, {"name": "visitsoutheastengland.com", "seller_id": "17902", "seller_type": "PUBLISHER"}, {"name": "visitsouthdevon.co.uk", "seller_id": "17901", "seller_type": "PUBLISHER"}, {"name": "visitplymouth.co.uk", "seller_id": "17900", "seller_type": "PUBLISHER"}, {"name": "visitpeterborough.com", "seller_id": "17899", "seller_type": "PUBLISHER"}, {"name": "visitpeakdistrict.com", "seller_id": "17898", "seller_type": "PUBLISHER"}, {"name": "visit-nottinghamshire.co.uk", "seller_id": "17897", "seller_type": "PUBLISHER"}, {"name": "thenewforest.co.uk", "seller_id": "17896", "seller_type": "PUBLISHER"}, {"name": "visitmanchester.com", "seller_id": "17895", "seller_type": "PUBLISHER"}, {"name": "visitmaidstone.com", "seller_id": "17894", "seller_type": "PUBLISHER"}, {"name": "visitliverpool.com", "seller_id": "17893", "seller_type": "PUBLISHER"}, {"name": "visitlancashire.com", "seller_id": "17892", "seller_type": "PUBLISHER"}, {"name": "lakedistrictweatherline.co.uk", "seller_id": "17891", "seller_type": "PUBLISHER"}, {"name": "visitlakedistrict.com", "seller_id": "17890", "seller_type": "PUBLISHER"}, {"name": "keswick.org", "seller_id": "17889", "seller_type": "PUBLISHER"}, {"name": "visitgreenwich.org.uk", "seller_id": "17888", "seller_type": "PUBLISHER"}, {"name": "visitharrogate.co.uk", "seller_id": "17887", "seller_type": "PUBLISHER"}, {"name": "thecityofgloucester.co.uk", "seller_id": "17886", "seller_type": "PUBLISHER"}, {"name": "fowey.co.uk", "seller_id": "17885", "seller_type": "PUBLISHER"}, {"name": "visitexeter.com", "seller_id": "17884", "seller_type": "PUBLISHER"}, {"name": "visitessex.com", "seller_id": "17883", "seller_type": "PUBLISHER"}, {"name": "visiteastbourne.com", "seller_id": "17882", "seller_type": "PUBLISHER"}, {"name": "thisisdurham.com", "seller_id": "17881", "seller_type": "PUBLISHER"}, {"name": "visit-dorset.com", "seller_id": "17880", "seller_type": "PUBLISHER"}, {"name": "visitdevon.co.uk", "seller_id": "17879", "seller_type": "PUBLISHER"}, {"name": "cotswolds.com", "seller_id": "17878", "seller_type": "PUBLISHER"}, {"name": "visitchesterfield.info", "seller_id": "17877", "seller_type": "PUBLISHER"}, {"name": "visitcheshire.com", "seller_id": "17876", "seller_type": "PUBLISHER"}, {"name": "visitcheltenham.com", "seller_id": "17875", "seller_type": "PUBLISHER"}, {"name": "visitbrighton.com", "seller_id": "17874", "seller_type": "PUBLISHER"}, {"name": "test2.jamiedruce.io", "seller_id": "17873", "seller_type": "PUBLISHER"}, {"name": "test.jamiedruce.io", "seller_id": "17872", "seller_type": "PUBLISHER"}, {"name": "dailymotion.com", "seller_id": "17871", "seller_type": "PUBLISHER"}, {"name": "rolloid.net", "seller_id": "17869", "seller_type": "PUBLISHER"}, {"name": "lsgeek.com", "seller_id": "17860", "seller_type": "PUBLISHER"}, {"name": "pczone.co.uk", "seller_id": "17859", "seller_type": "PUBLISHER"}, {"name": "dailymail.co.uk", "seller_id": "17858", "seller_type": "PUBLISHER"}, {"name": "visitbath.co.uk", "seller_id": "17857", "seller_type": "PUBLISHER"}, {"name": "agriculturaltrader.co.uk", "seller_id": "17856", "seller_type": "PUBLISHER"}, {"name": "ukga.com", "seller_id": "17855", "seller_type": "PUBLISHER"}, {"name": "bridemagazine.co.uk", "seller_id": "17854", "seller_type": "PUBLISHER"}, {"name": "peterboroughmatters.co.uk", "seller_id": "17853", "seller_type": "PUBLISHER"}, {"name": "torbayweekly.co.uk", "seller_id": "17852", "seller_type": "PUBLISHER"}, {"name": "ripongazette.co.uk", "seller_id": "17851", "seller_type": "PUBLISHER"}, {"name": "hemsworthandsouthelmsallexpress.co.uk", "seller_id": "17850", "seller_type": "PUBLISHER"}, {"name": "anguscountyworld.co.uk", "seller_id": "17849", "seller_type": "PUBLISHER"}, {"name": "northernirelandworld.com", "seller_id": "17848", "seller_type": "PUBLISHER"}, {"name": "kidadl.com", "seller_id": "17847", "seller_type": "PUBLISHER"}, {"name": "localsearch24.co.uk", "seller_id": "17846", "seller_type": "PUBLISHER"}, {"name": "glasgowworld.com", "seller_id": "17844", "seller_type": "PUBLISHER"}, {"name": "yourlocalguardian.co.uk", "seller_id": "17842", "seller_type": "PUBLISHER"}, {"name": "yorkpress.co.uk", "seller_id": "17841", "seller_type": "PUBLISHER"}, {"name": "yeovilexpress.co.uk", "seller_id": "17840", "seller_type": "PUBLISHER"}, {"name": "worcesternews.co.uk", "seller_id": "17839", "seller_type": "PUBLISHER"}, {"name": "witneygazette.co.uk", "seller_id": "17838", "seller_type": "PUBLISHER"}, {"name": "wirralglobe.co.uk", "seller_id": "17837", "seller_type": "PUBLISHER"}, {"name": "winsfordguardian.co.uk", "seller_id": "17836", "seller_type": "PUBLISHER"}, {"name": "wimbledonguardian.co.uk", "seller_id": "17835", "seller_type": "PUBLISHER"}, {"name": "wiltshiretimes.co.uk", "seller_id": "17834", "seller_type": "PUBLISHER"}, {"name": "wiltsglosstandard.co.uk", "seller_id": "17833", "seller_type": "PUBLISHER"}, {"name": "whitehavennews.co.uk", "seller_id": "17832", "seller_type": "PUBLISHER"}, {"name": "whitchurchherald.co.uk", "seller_id": "17831", "seller_type": "PUBLISHER"}, {"name": "wharfedaleobserver.co.uk", "seller_id": "17830", "seller_type": "PUBLISHER"}, {"name": "westerntelegraph.co.uk", "seller_id": "17829", "seller_type": "PUBLISHER"}, {"name": "wearevoice.co.uk", "seller_id": "17828", "seller_type": "PUBLISHER"}, {"name": "watfordobserver.co.uk", "seller_id": "17827", "seller_type": "PUBLISHER"}, {"name": "warringtonguardian.co.uk", "seller_id": "17826", "seller_type": "PUBLISHER"}, {"name": "wandsworthguardian.co.uk", "seller_id": "17825", "seller_type": "PUBLISHER"}, {"name": "walesfarmer.co.uk", "seller_id": "17824", "seller_type": "PUBLISHER"}, {"name": "thetottenhamindependent.co.uk", "seller_id": "17822", "seller_type": "PUBLISHER"}, {"name": "tivysideadvertiser.co.uk", "seller_id": "17821", "seller_type": "PUBLISHER"}, {"name": "times-series.co.uk", "seller_id": "17820", "seller_type": "PUBLISHER"}, {"name": "timesandstar.co.uk", "seller_id": "17819", "seller_type": "PUBLISHER"}, {"name": "thurrockgazette.co.uk", "seller_id": "17818", "seller_type": "PUBLISHER"}, {"name": "thisisoxfordshire.co.uk", "seller_id": "17817", "seller_type": "PUBLISHER"}, {"name": "thisiswiltshire.co.uk", "seller_id": "17816", "seller_type": "PUBLISHER"}, {"name": "thisislocallondon.co.uk", "seller_id": "17814", "seller_type": "PUBLISHER"}, {"name": "gazetteandherald.co.uk", "seller_id": "17812", "seller_type": "PUBLISHER"}, {"name": "thewestmorlandgazette.co.uk", "seller_id": "17811", "seller_type": "PUBLISHER"}, {"name": "thescottishfarmer.co.uk", "seller_id": "17810", "seller_type": "PUBLISHER"}, {"name": "theoldhamtimes.co.uk", "seller_id": "17809", "seller_type": "PUBLISHER"}, {"name": "northernfarmer.co.uk", "seller_id": "17808", "seller_type": "PUBLISHER"}, {"name": "thenorthernecho.co.uk", "seller_id": "17807", "seller_type": "PUBLISHER"}, {"name": "thenational.scot", "seller_id": "17806", "seller_type": "PUBLISHER"}, {"name": "nwemail.co.uk", "seller_id": "17805", "seller_type": "PUBLISHER"}, {"name": "leaderlive.co.uk", "seller_id": "17804", "seller_type": "PUBLISHER"}, {"name": "theinterestingtimes.co.uk", "seller_id": "17803", "seller_type": "PUBLISHER"}, {"name": "the-gazette.co.uk", "seller_id": "17801", "seller_type": "PUBLISHER"}, {"name": "theboltonnews.co.uk", "seller_id": "17800", "seller_type": "PUBLISHER"}, {"name": "theargus.co.uk", "seller_id": "17799", "seller_type": "PUBLISHER"}, {"name": "swindonadvertiser.co.uk", "seller_id": "17797", "seller_type": "PUBLISHER"}, {"name": "swanageandwarehamvoice.co.uk", "seller_id": "17796", "seller_type": "PUBLISHER"}, {"name": "surreycomet.co.uk", "seller_id": "17795", "seller_type": "PUBLISHER"}, {"name": "stroudnewsandjournal.co.uk", "seller_id": "17794", "seller_type": "PUBLISHER"}, {"name": "strathallantimes.co.uk", "seller_id": "17793", "seller_type": "PUBLISHER"}, {"name": "stourbridgenews.co.uk", "seller_id": "17792", "seller_type": "PUBLISHER"}, {"name": "stirlingnews.co.uk", "seller_id": "17791", "seller_type": "PUBLISHER"}, {"name": "sthelensstar.co.uk", "seller_id": "17790", "seller_type": "PUBLISHER"}, {"name": "stalbansreview.co.uk", "seller_id": "17789", "seller_type": "PUBLISHER"}, {"name": "southwestfarmer.co.uk", "seller_id": "17787", "seller_type": "PUBLISHER"}, {"name": "southwalesguardian.co.uk", "seller_id": "17786", "seller_type": "PUBLISHER"}, {"name": "southwalesargus.co.uk", "seller_id": "17785", "seller_type": "PUBLISHER"}, {"name": "somersetcountygazette.co.uk", "seller_id": "17784", "seller_type": "PUBLISHER"}, {"name": "sloughobserver.co.uk", "seller_id": "17783", "seller_type": "PUBLISHER"}, {"name": "salisburyjournal.co.uk", "seller_id": "17782", "seller_type": "PUBLISHER"}, {"name": "runcornandwidnesworld.co.uk", "seller_id": "17780", "seller_type": "PUBLISHER"}, {"name": "windsorobserver.co.uk", "seller_id": "17779", "seller_type": "PUBLISHER"}, {"name": "romseyadvertiser.co.uk", "seller_id": "17778", "seller_type": "PUBLISHER"}, {"name": "richmondandtwickenhamtimes.co.uk", "seller_id": "17777", "seller_type": "PUBLISHER"}, {"name": "rhyljournal.co.uk", "seller_id": "17776", "seller_type": "PUBLISHER"}, {"name": "redhillandreigatelife.co.uk", "seller_id": "17775", "seller_type": "PUBLISHER"}, {"name": "redditchadvertiser.co.uk", "seller_id": "17774", "seller_type": "PUBLISHER"}, {"name": "readingchronicle.co.uk", "seller_id": "17773", "seller_type": "PUBLISHER"}, {"name": "penarthtimes.co.uk", "seller_id": "17771", "seller_type": "PUBLISHER"}, {"name": "peeblesshirenews.com", "seller_id": "17770", "seller_type": "PUBLISHER"}, {"name": "oxfordmail.co.uk", "seller_id": "17769", "seller_type": "PUBLISHER"}, {"name": "northwichguardian.co.uk", "seller_id": "17768", "seller_type": "PUBLISHER"}, {"name": "northwalespioneer.co.uk", "seller_id": "17767", "seller_type": "PUBLISHER"}, {"name": "northwaleschronicle.co.uk", "seller_id": "17766", "seller_type": "PUBLISHER"}, {"name": "newsshopper.co.uk", "seller_id": "17764", "seller_type": "PUBLISHER"}, {"name": "newsandstar.co.uk", "seller_id": "17763", "seller_type": "PUBLISHER"}, {"name": "newforestpost.co.uk", "seller_id": "17762", "seller_type": "PUBLISHER"}, {"name": "milfordmercury.co.uk", "seller_id": "17761", "seller_type": "PUBLISHER"}, {"name": "messengernewspapers.co.uk", "seller_id": "17760", "seller_type": "PUBLISHER"}, {"name": "malverngazette.co.uk", "seller_id": "17759", "seller_type": "PUBLISHER"}, {"name": "maldonandburnhamstandard.co.uk", "seller_id": "17758", "seller_type": "PUBLISHER"}, {"name": "ludlowadvertiser.co.uk", "seller_id": "17757", "seller_type": "PUBLISHER"}, {"name": "leighjournal.co.uk", "seller_id": "17755", "seller_type": "PUBLISHER"}, {"name": "ledburyreporter.co.uk", "seller_id": "17754", "seller_type": "PUBLISHER"}, {"name": "largsandmillportnews.com", "seller_id": "17753", "seller_type": "PUBLISHER"}, {"name": "lancashiretelegraph.co.uk", "seller_id": "17751", "seller_type": "PUBLISHER"}, {"name": "knutsfordguardian.co.uk", "seller_id": "17750", "seller_type": "PUBLISHER"}, {"name": "kidderminstershuttle.co.uk", "seller_id": "17749", "seller_type": "PUBLISHER"}, {"name": "keighleynews.co.uk", "seller_id": "17748", "seller_type": "PUBLISHER"}, {"name": "countypress.co.uk", "seller_id": "17747", "seller_type": "PUBLISHER"}, {"name": "irvinetimes.com", "seller_id": "17746", "seller_type": "PUBLISHER"}, {"name": "in-cumbria.com", "seller_id": "17745", "seller_type": "PUBLISHER"}, {"name": "impartialreporter.com", "seller_id": "17743", "seller_type": "PUBLISHER"}, {"name": "ilkleygazette.co.uk", "seller_id": "17742", "seller_type": "PUBLISHER"}, {"name": "hillingdontimes.co.uk", "seller_id": "17741", "seller_type": "PUBLISHER"}, {"name": "hexham-courant.co.uk", "seller_id": "17740", "seller_type": "PUBLISHER"}, {"name": "herefordtimes.com", "seller_id": "17739", "seller_type": "PUBLISHER"}, {"name": "heraldscotland.com", "seller_id": "17738", "seller_type": "PUBLISHER"}, {"name": "heraldseries.co.uk", "seller_id": "17737", "seller_type": "PUBLISHER"}, {"name": "helensburghadvertiser.co.uk", "seller_id": "17736", "seller_type": "PUBLISHER"}, {"name": "harwichandmanningtreestandard.co.uk", "seller_id": "17735", "seller_type": "PUBLISHER"}, {"name": "harrowtimes.co.uk", "seller_id": "17734", "seller_type": "PUBLISHER"}, {"name": "hampshirechronicle.co.uk", "seller_id": "17733", "seller_type": "PUBLISHER"}, {"name": "halsteadgazette.co.uk", "seller_id": "17732", "seller_type": "PUBLISHER"}, {"name": "halesowennews.co.uk", "seller_id": "17731", "seller_type": "PUBLISHER"}, {"name": "greenocktelegraph.co.uk", "seller_id": "17730", "seller_type": "PUBLISHER"}, {"name": "glasgowtimes.co.uk", "seller_id": "17729", "seller_type": "PUBLISHER"}, {"name": "gazetteseries.co.uk", "seller_id": "17728", "seller_type": "PUBLISHER"}, {"name": "gazetteherald.co.uk", "seller_id": "17727", "seller_type": "PUBLISHER"}, {"name": "gazette-news.co.uk", "seller_id": "17726", "seller_type": "PUBLISHER"}, {"name": "freepressseries.co.uk", "seller_id": "17725", "seller_type": "PUBLISHER"}, {"name": "forestryjournal.co.uk", "seller_id": "17724", "seller_type": "PUBLISHER"}, {"name": "falmouthpacket.co.uk", "seller_id": "17723", "seller_type": "PUBLISHER"}, {"name": "eveshamjournal.co.uk", "seller_id": "17722", "seller_type": "PUBLISHER"}, {"name": "eppingforestguardian.co.uk", "seller_id": "17718", "seller_type": "PUBLISHER"}, {"name": "enfieldindependent.co.uk", "seller_id": "17717", "seller_type": "PUBLISHER"}, {"name": "echo-news.co.uk", "seller_id": "17716", "seller_type": "PUBLISHER"}, {"name": "eastlothiancourier.com", "seller_id": "17715", "seller_type": "PUBLISHER"}, {"name": "guardian-series.co.uk", "seller_id": "17714", "seller_type": "PUBLISHER"}, {"name": "eastkilbrideconnect.co.uk", "seller_id": "17713", "seller_type": "PUBLISHER"}, {"name": "ealingtimes.co.uk", "seller_id": "17712", "seller_type": "PUBLISHER"}, {"name": "dunfermlinepress.com", "seller_id": "17711", "seller_type": "PUBLISHER"}, {"name": "dumbartonreporter.co.uk", "seller_id": "17710", "seller_type": "PUBLISHER"}, {"name": "dudleynews.co.uk", "seller_id": "17709", "seller_type": "PUBLISHER"}, {"name": "dorsetecho.co.uk", "seller_id": "17706", "seller_type": "PUBLISHER"}, {"name": "denbighshirefreepress.co.uk", "seller_id": "17703", "seller_type": "PUBLISHER"}, {"name": "darlingtonandstocktontimes.co.uk", "seller_id": "17702", "seller_type": "PUBLISHER"}, {"name": "cumnockchronicle.com", "seller_id": "17700", "seller_type": "PUBLISHER"}, {"name": "cravenherald.co.uk", "seller_id": "17699", "seller_type": "PUBLISHER"}, {"name": "countytimes.co.uk", "seller_id": "17698", "seller_type": "PUBLISHER"}, {"name": "cotswoldjournal.co.uk", "seller_id": "17697", "seller_type": "PUBLISHER"}, {"name": "clydebankpost.co.uk", "seller_id": "17696", "seller_type": "PUBLISHER"}, {"name": "clactonandfrintongazette.co.uk", "seller_id": "17695", "seller_type": "PUBLISHER"}, {"name": "chesterstandard.co.uk", "seller_id": "17693", "seller_type": "PUBLISHER"}, {"name": "chelmsfordweeklynews.co.uk", "seller_id": "17692", "seller_type": "PUBLISHER"}, {"name": "chardandilminsternews.co.uk", "seller_id": "17691", "seller_type": "PUBLISHER"}, {"name": "centralfifetimes.com", "seller_id": "17690", "seller_type": "PUBLISHER"}, {"name": "burytimes.co.uk", "seller_id": "17686", "seller_type": "PUBLISHER"}, {"name": "burnhamandhighbridgeweeklynews.co.uk", "seller_id": "17685", "seller_type": "PUBLISHER"}, {"name": "bucksfreepress.co.uk", "seller_id": "17684", "seller_type": "PUBLISHER"}, {"name": "bromsgroveadvertiser.co.uk", "seller_id": "17683", "seller_type": "PUBLISHER"}, {"name": "bridportnews.co.uk", "seller_id": "17682", "seller_type": "PUBLISHER"}, {"name": "bridgwatermercury.co.uk", "seller_id": "17681", "seller_type": "PUBLISHER"}, {"name": "brentwoodlive.co.uk", "seller_id": "17680", "seller_type": "PUBLISHER"}, {"name": "braintreeandwithamtimes.co.uk", "seller_id": "17679", "seller_type": "PUBLISHER"}, {"name": "thetelegraphandargus.co.uk", "seller_id": "17678", "seller_type": "PUBLISHER"}, {"name": "bracknellnews.co.uk", "seller_id": "17677", "seller_type": "PUBLISHER"}, {"name": "bournemouthecho.co.uk", "seller_id": "17676", "seller_type": "PUBLISHER"}, {"name": "borehamwoodtimes.co.uk", "seller_id": "17675", "seller_type": "PUBLISHER"}, {"name": "bordertelegraph.com", "seller_id": "17674", "seller_type": "PUBLISHER"}, {"name": "bordercountiesadvertizer.co.uk", "seller_id": "17673", "seller_type": "PUBLISHER"}, {"name": "basingstokegazette.co.uk", "seller_id": "17671", "seller_type": "PUBLISHER"}, {"name": "barryanddistrictnews.co.uk", "seller_id": "17669", "seller_type": "PUBLISHER"}, {"name": "barrheadnews.com", "seller_id": "17668", "seller_type": "PUBLISHER"}, {"name": "banburycake.co.uk", "seller_id": "17667", "seller_type": "PUBLISHER"}, {"name": "ayradvertiser.com", "seller_id": "17666", "seller_type": "PUBLISHER"}, {"name": "autoexchange.co.uk", "seller_id": "17665", "seller_type": "PUBLISHER"}, {"name": "asianimage.co.uk", "seller_id": "17664", "seller_type": "PUBLISHER"}, {"name": "ardrossanherald.com", "seller_id": "17663", "seller_type": "PUBLISHER"}, {"name": "andoveradvertiser.co.uk", "seller_id": "17662", "seller_type": "PUBLISHER"}, {"name": "alloaadvertiser.com", "seller_id": "17661", "seller_type": "PUBLISHER"}, {"name": "yorkshirepost.co.uk", "seller_id": "17660", "seller_type": "PUBLISHER"}, {"name": "yorkshireeveningpost.co.uk", "seller_id": "17659", "seller_type": "PUBLISHER"}, {"name": "worksopguardian.co.uk", "seller_id": "17657", "seller_type": "PUBLISHER"}, {"name": "wigantoday.net", "seller_id": "17656", "seller_type": "PUBLISHER"}, {"name": "westsussextoday.co.uk", "seller_id": "17653", "seller_type": "PUBLISHER"}, {"name": "wscountytimes.co.uk", "seller_id": "17652", "seller_type": "PUBLISHER"}, {"name": "warwickshireworld.com", "seller_id": "17651", "seller_type": "PUBLISHER"}, {"name": "wakefieldexpress.co.uk", "seller_id": "17648", "seller_type": "PUBLISHER"}, {"name": "thevisitor.co.uk", "seller_id": "17644", "seller_type": "PUBLISHER"}, {"name": "thestar.co.uk", "seller_id": "17643", "seller_type": "PUBLISHER"}, {"name": "thesouthernreporter.co.uk", "seller_id": "17642", "seller_type": "PUBLISHER"}, {"name": "portsmouth.co.uk", "seller_id": "17641", "seller_type": "PUBLISHER"}, {"name": "sussexexpress.co.uk", "seller_id": "17640", "seller_type": "PUBLISHER"}, {"name": "sunderlandecho.com", "seller_id": "17639", "seller_type": "PUBLISHER"}, {"name": "stornowaygazette.co.uk", "seller_id": "17638", "seller_type": "PUBLISHER"}, {"name": "sthelensreporter.co.uk", "seller_id": "17637", "seller_type": "PUBLISHER"}, {"name": "shorehamherald.co.uk", "seller_id": "17634", "seller_type": "PUBLISHER"}, {"name": "shieldsgazette.com", "seller_id": "17633", "seller_type": "PUBLISHER"}, {"name": "sheffieldtelegraph.co.uk", "seller_id": "17632", "seller_type": "PUBLISHER"}, {"name": "scotsman.com", "seller_id": "17631", "seller_type": "PUBLISHER"}, {"name": "thescarboroughnews.co.uk", "seller_id": "17630", "seller_type": "PUBLISHER"}, {"name": "peterboroughtoday.co.uk", "seller_id": "17622", "seller_type": "PUBLISHER"}, {"name": "northumberlandgazette.co.uk", "seller_id": "17620", "seller_type": "PUBLISHER"}, {"name": "northantstelegraph.co.uk", "seller_id": "17619", "seller_type": "PUBLISHER"}, {"name": "northamptonchron.co.uk", "seller_id": "17618", "seller_type": "PUBLISHER"}, {"name": "newsletter.co.uk", "seller_id": "17616", "seller_type": "PUBLISHER"}, {"name": "newcastleworld.com", "seller_id": "17613", "seller_type": "PUBLISHER"}, {"name": "nationalworld.com", "seller_id": "17612", "seller_type": "PUBLISHER"}, {"name": "miltonkeynes.co.uk", "seller_id": "17609", "seller_type": "PUBLISHER"}, {"name": "midhurstandpetworth.co.uk", "seller_id": "17607", "seller_type": "PUBLISHER"}, {"name": "midsussextimes.co.uk", "seller_id": "17605", "seller_type": "PUBLISHER"}, {"name": "meltontimes.co.uk", "seller_id": "17604", "seller_type": "PUBLISHER"}, {"name": "mearnsleader.co.uk", "seller_id": "17603", "seller_type": "PUBLISHER"}, {"name": "matlockmercury.co.uk", "seller_id": "17602", "seller_type": "PUBLISHER"}, {"name": "chad.co.uk", "seller_id": "17601", "seller_type": "PUBLISHER"}, {"name": "manchesterworld.uk", "seller_id": "17600", "seller_type": "PUBLISHER"}, {"name": "lutontoday.co.uk", "seller_id": "17598", "seller_type": "PUBLISHER"}, {"name": "londonworld.com", "seller_id": "17596", "seller_type": "PUBLISHER"}, {"name": "liverpoolworld.uk", "seller_id": "17594", "seller_type": "PUBLISHER"}, {"name": "littlehamptongazette.co.uk", "seller_id": "17593", "seller_type": "PUBLISHER"}, {"name": "lincolnshireworld.com", "seller_id": "17591", "seller_type": "PUBLISHER"}, {"name": "leightonbuzzardonline.co.uk", "seller_id": "17590", "seller_type": "PUBLISHER"}, {"name": "lancasterguardian.co.uk", "seller_id": "17587", "seller_type": "PUBLISHER"}, {"name": "lep.co.uk", "seller_id": "17586", "seller_type": "PUBLISHER"}, {"name": "kincardineshireobserver.co.uk", "seller_id": "17585", "seller_type": "PUBLISHER"}, {"name": "inverurieherald.co.uk", "seller_id": "17583", "seller_type": "PUBLISHER"}, {"name": "hucknalldispatch.co.uk", "seller_id": "17581", "seller_type": "PUBLISHER"}, {"name": "hemeltoday.co.uk", "seller_id": "17579", "seller_type": "PUBLISHER"}, {"name": "hastingsobserver.co.uk", "seller_id": "17577", "seller_type": "PUBLISHER"}, {"name": "hartlepoolmail.co.uk", "seller_id": "17576", "seller_type": "PUBLISHER"}, {"name": "harrogateadvertiser.co.uk", "seller_id": "17575", "seller_type": "PUBLISHER"}, {"name": "harboroughmail.co.uk", "seller_id": "17574", "seller_type": "PUBLISHER"}, {"name": "halifaxcourier.co.uk", "seller_id": "17573", "seller_type": "PUBLISHER"}, {"name": "gallowaygazette.co.uk", "seller_id": "17570", "seller_type": "PUBLISHER"}, {"name": "fraserburghherald.co.uk", "seller_id": "17569", "seller_type": "PUBLISHER"}, {"name": "fifetoday.co.uk", "seller_id": "17567", "seller_type": "PUBLISHER"}, {"name": "farminglife.com", "seller_id": "17566", "seller_type": "PUBLISHER"}, {"name": "falkirkherald.co.uk", "seller_id": "17565", "seller_type": "PUBLISHER"}, {"name": "ellontimes.co.uk", "seller_id": "17564", "seller_type": "PUBLISHER"}, {"name": "edinburghnews.scotsman.com", "seller_id": "17563", "seller_type": "PUBLISHER"}, {"name": "eastwoodadvertiser.co.uk", "seller_id": "17562", "seller_type": "PUBLISHER"}, {"name": "eastbourneherald.co.uk", "seller_id": "17561", "seller_type": "PUBLISHER"}, {"name": "donsidepiper.co.uk", "seller_id": "17559", "seller_type": "PUBLISHER"}, {"name": "doncasterfreepress.co.uk", "seller_id": "17558", "seller_type": "PUBLISHER"}, {"name": "dewsburyreporter.co.uk", "seller_id": "17557", "seller_type": "PUBLISHER"}, {"name": "derryjournal.com", "seller_id": "17556", "seller_type": "PUBLISHER"}, {"name": "derbyshiretimes.co.uk", "seller_id": "17555", "seller_type": "PUBLISHER"}, {"name": "deesidepiper.co.uk", "seller_id": "17554", "seller_type": "PUBLISHER"}, {"name": "daventryexpress.co.uk", "seller_id": "17553", "seller_type": "PUBLISHER"}, {"name": "crawleyobserver.co.uk", "seller_id": "17552", "seller_type": "PUBLISHER"}, {"name": "clitheroeadvertiser.co.uk", "seller_id": "17550", "seller_type": "PUBLISHER"}, {"name": "chichester.co.uk", "seller_id": "17548", "seller_type": "PUBLISHER"}, {"name": "buxtonadvertiser.co.uk", "seller_id": "17546", "seller_type": "PUBLISHER"}, {"name": "burnleyexpress.net", "seller_id": "17545", "seller_type": "PUBLISHER"}, {"name": "bucksherald.co.uk", "seller_id": "17544", "seller_type": "PUBLISHER"}, {"name": "buchanobserver.co.uk", "seller_id": "17542", "seller_type": "PUBLISHER"}, {"name": "bristolworld.com", "seller_id": "17541", "seller_type": "PUBLISHER"}, {"name": "brightonandhoveindependent.co.uk", "seller_id": "17540", "seller_type": "PUBLISHER"}, {"name": "bognor.co.uk", "seller_id": "17537", "seller_type": "PUBLISHER"}, {"name": "blackpoolgazette.co.uk", "seller_id": "17536", "seller_type": "PUBLISHER"}, {"name": "birminghamworld.uk", "seller_id": "17535", "seller_type": "PUBLISHER"}, {"name": "biggleswadetoday.co.uk", "seller_id": "17534", "seller_type": "PUBLISHER"}, {"name": "bexhillobserver.net", "seller_id": "17533", "seller_type": "PUBLISHER"}, {"name": "check.jamiedruce.io", "seller_id": "17532", "seller_type": "PUBLISHER"}, {"name": "leitrimobserver.ie", "seller_id": "17530", "seller_type": "PUBLISHER"}, {"name": "carlowlive.ie", "seller_id": "17529", "seller_type": "PUBLISHER"}, {"name": "tipperarylive.ie", "seller_id": "17527", "seller_type": "PUBLISHER"}, {"name": "ireland-live.ie", "seller_id": "17526", "seller_type": "PUBLISHER"}, {"name": "waterfordlive.ie", "seller_id": "17525", "seller_type": "PUBLISHER"}, {"name": "offalyexpress.ie", "seller_id": "17524", "seller_type": "PUBLISHER"}, {"name": "nenaghlive.ie", "seller_id": "17523", "seller_type": "PUBLISHER"}, {"name": "longfordleader.ie", "seller_id": "17522", "seller_type": "PUBLISHER"}, {"name": "limerickleader.ie", "seller_id": "17521", "seller_type": "PUBLISHER"}, {"name": "leinsterleader.ie", "seller_id": "17520", "seller_type": "PUBLISHER"}, {"name": "kilkennypeople.ie", "seller_id": "17519", "seller_type": "PUBLISHER"}, {"name": "kildarenow.com", "seller_id": "17518", "seller_type": "PUBLISHER"}, {"name": "inishlive.ie", "seller_id": "17517", "seller_type": "PUBLISHER"}, {"name": "dundalkdemocrat.ie", "seller_id": "17516", "seller_type": "PUBLISHER"}, {"name": "donegallive.ie", "seller_id": "17515", "seller_type": "PUBLISHER"}, {"name": "derrynow.com", "seller_id": "17514", "seller_type": "PUBLISHER"}, {"name": "corklive.ie", "seller_id": "17513", "seller_type": "PUBLISHER"}, {"name": "ClareLive.ie", "seller_id": "17512", "seller_type": "PUBLISHER"}, {"name": "berwickshirenews.co.uk", "seller_id": "17511", "seller_type": "PUBLISHER"}, {"name": "bedfordtoday.co.uk", "seller_id": "17508", "seller_type": "PUBLISHER"}, {"name": "banburyguardian.co.uk", "seller_id": "17506", "seller_type": "PUBLISHER"}, {"name": "stowmarketmercury.co.uk", "seller_id": "17502", "seller_type": "PUBLISHER"}, {"name": "rifleshootermagazine.co.uk", "seller_id": "17501", "seller_type": "PUBLISHER"}, {"name": "midweekherald.co.uk", "seller_id": "17500", "seller_type": "PUBLISHER"}, {"name": "ilfordrecorder.co.uk", "seller_id": "17499", "seller_type": "PUBLISHER"}, {"name": "eastlondonadvertiser.co.uk", "seller_id": "17498", "seller_type": "PUBLISHER"}, {"name": "derehamtimes.co.uk", "seller_id": "17497", "seller_type": "PUBLISHER"}, {"name": "wymondhamandattleboroughmercury.co.uk", "seller_id": "17493", "seller_type": "PUBLISHER"}, {"name": "wisbechstandard.co.uk", "seller_id": "17491", "seller_type": "PUBLISHER"}, {"name": "whtimes.co.uk", "seller_id": "17490", "seller_type": "PUBLISHER"}, {"name": "wattonandswaffhamtimes.co.uk", "seller_id": "17487", "seller_type": "PUBLISHER"}, {"name": "thewestonmercury.co.uk", "seller_id": "17484", "seller_type": "PUBLISHER"}, {"name": "thetfordandbrandontimes.co.uk", "seller_id": "17483", "seller_type": "PUBLISHER"}, {"name": "theresident.co.uk", "seller_id": "17482", "seller_type": "PUBLISHER"}, {"name": "theneweuropean.co.uk", "seller_id": "17481", "seller_type": "PUBLISHER"}, {"name": "thecomet.net", "seller_id": "17480", "seller_type": "PUBLISHER"}, {"name": "sudburymercury.co.uk", "seller_id": "17474", "seller_type": "PUBLISHER"}, {"name": "sportingshooter.co.uk", "seller_id": "17473", "seller_type": "PUBLISHER"}, {"name": "sidmouthherald.co.uk", "seller_id": "17470", "seller_type": "PUBLISHER"}, {"name": "saffronwaldenreporter.co.uk", "seller_id": "17469", "seller_type": "PUBLISHER"}, {"name": "royston-crow.co.uk", "seller_id": "17468", "seller_type": "PUBLISHER"}, {"name": "romfordrecorder.co.uk", "seller_id": "17467", "seller_type": "PUBLISHER"}, {"name": "pinkun.com", "seller_id": "17466", "seller_type": "PUBLISHER"}, {"name": "pilotweb.aero", "seller_id": "17465", "seller_type": "PUBLISHER"}, {"name": "northsomersettimes.co.uk", "seller_id": "17464", "seller_type": "PUBLISHER"}, {"name": "northnorfolknews.co.uk", "seller_id": "17463", "seller_type": "PUBLISHER"}, {"name": "northdevongazette.co.uk", "seller_id": "17462", "seller_type": "PUBLISHER"}, {"name": "newhamrecorder.co.uk", "seller_id": "17460", "seller_type": "PUBLISHER"}, {"name": "bentest.com", "seller_id": "17457", "seller_type": "PUBLISHER"}, {"name": "leinsterexpress.ie", "seller_id": "17456", "seller_type": "PUBLISHER"}, {"name": "motorsport.com", "seller_id": "17455", "seller_type": "PUBLISHER"}, {"name": "worthingherald.co.uk", "seller_id": "17454", "seller_type": "PUBLISHER"}, {"name": "tune-flix.com", "seller_id": "17453", "seller_type": "PUBLISHER"}, {"name": "gearculture.com", "seller_id": "17450", "seller_type": "PUBLISHER"}, {"name": "sli.ce.it", "seller_id": "17449", "seller_type": "PUBLISHER"}, {"name": "sli.ce.it", "seller_id": "17448", "seller_type": "PUBLISHER"}, {"name": "rdg.today", "seller_id": "17447", "seller_type": "PUBLISHER"}, {"name": "wokingham.today", "seller_id": "17446", "seller_type": "PUBLISHER"}, {"name": "iconicnews.ie", "seller_id": "17445", "seller_type": "PUBLISHER"}, {"name": "blog.hole19golf.com", "seller_id": "17444", "seller_type": "PUBLISHER"}, {"name": "techexplains.com", "seller_id": "17443", "seller_type": "PUBLISHER"}, {"name": "lowestoftjournal.co.uk", "seller_id": "17442", "seller_type": "PUBLISHER"}, {"name": "kilburntimes.co.uk", "seller_id": "17438", "seller_type": "PUBLISHER"}, {"name": "islingtongazette.co.uk", "seller_id": "17435", "seller_type": "PUBLISHER"}, {"name": "ipswichstar.co.uk", "seller_id": "17434", "seller_type": "PUBLISHER"}, {"name": "huntspost.co.uk", "seller_id": "17433", "seller_type": "PUBLISHER"}, {"name": "hertsad.co.uk", "seller_id": "17432", "seller_type": "PUBLISHER"}, {"name": "hamhigh.co.uk", "seller_id": "17429", "seller_type": "PUBLISHER"}, {"name": "hackneygazette.co.uk", "seller_id": "17428", "seller_type": "PUBLISHER"}, {"name": "greenun24.co.uk", "seller_id": "17427", "seller_type": "PUBLISHER"}, {"name": "greatyarmouthmercury.co.uk", "seller_id": "17426", "seller_type": "PUBLISHER"}, {"name": "francepropertyshop.com", "seller_id": "17423", "seller_type": "PUBLISHER"}, {"name": "fakenhamtimes.co.uk", "seller_id": "17422", "seller_type": "PUBLISHER"}, {"name": "exmouthjournal.co.uk", "seller_id": "17421", "seller_type": "PUBLISHER"}, {"name": "eveningnews24.co.uk", "seller_id": "17420", "seller_type": "PUBLISHER"}, {"name": "elystandard.co.uk", "seller_id": "17418", "seller_type": "PUBLISHER"}, {"name": "edp24.co.uk", "seller_id": "17417", "seller_type": "PUBLISHER"}, {"name": "eastdevon24.co.uk", "seller_id": "17416", "seller_type": "PUBLISHER"}, {"name": "eadt.co.uk", "seller_id": "17415", "seller_type": "PUBLISHER"}, {"name": "dunmowbroadcast.co.uk", "seller_id": "17414", "seller_type": "PUBLISHER"}, {"name": "dissmercury.co.uk", "seller_id": "17412", "seller_type": "PUBLISHER"}, {"name": "devonlife.co.uk", "seller_id": "17411", "seller_type": "PUBLISHER"}, {"name": "countrysmallholding.com", "seller_id": "17409", "seller_type": "PUBLISHER"}, {"name": "chesirelife.co.uk", "seller_id": "17405", "seller_type": "PUBLISHER"}, {"name": "canalboat.co.uk", "seller_id": "17404", "seller_type": "PUBLISHER"}, {"name": "cambstimes.co.uk", "seller_id": "17403", "seller_type": "PUBLISHER"}, {"name": "burymercury.co.uk", "seller_id": "17402", "seller_type": "PUBLISHER"}, {"name": "becclesandbungayjournal.co.uk", "seller_id": "17397", "seller_type": "PUBLISHER"}, {"name": "barkinganddagenhampost.co.uk", "seller_id": "17396", "seller_type": "PUBLISHER"}, {"name": "airgunshooting.co.uk", "seller_id": "17395", "seller_type": "PUBLISHER"}, {"name": "newspublisher.co.uk", "seller_id": "17393", "seller_type": "PUBLISHER"}, {"name": "winningfamilies.iwcomps.com", "seller_id": "17392", "seller_type": "PUBLISHER"}, {"name": "giftcards.iwcomps.com", "seller_id": "17391", "seller_type": "PUBLISHER"}, {"name": "skintdad.iwcomps.com", "seller_id": "17390", "seller_type": "PUBLISHER"}, {"name": "pmpcomps.iwcomps.com", "seller_id": "17389", "seller_type": "PUBLISHER"}, {"name": "freecompetitions.iwcomps.com", "seller_id": "17388", "seller_type": "PUBLISHER"}, {"name": "nationalrail.co.uk", "seller_id": "17386", "seller_type": "PUBLISHER"}, {"name": "ruck.co.uk", "seller_id": "17385", "seller_type": "PUBLISHER"}, {"name": "avforums.com", "seller_id": "17384", "seller_type": "PUBLISHER"}, {"name": "voetbalzone.nl", "seller_id": "17383", "seller_type": "PUBLISHER"}, {"name": "vmovies.org", "seller_id": "17371", "seller_type": "PUBLISHER"}, {"name": "haneeffactdiary.com", "seller_id": "17370", "seller_type": "PUBLISHER"}, {"name": "shortlist.com", "seller_id": "17369", "seller_type": "PUBLISHER"}, {"name": "dcrainmaker.com", "seller_id": "17368", "seller_type": "PUBLISHER"}, {"name": "cyclesprog.co.uk", "seller_id": "17367", "seller_type": "PUBLISHER"}, {"name": "spotrac.com", "seller_id": "17366", "seller_type": "PUBLISHER"}, {"name": "zwiftinsider.com", "seller_id": "17365", "seller_type": "PUBLISHER"}, {"name": "autosport.com", "seller_id": "17314", "seller_type": "PUBLISHER"}, {"name": "saas.scifinow.co.uk", "seller_id": "17313", "seller_type": "PUBLISHER"}, {"name": "cencelx.com", "seller_id": "17312", "seller_type": "PUBLISHER"}, {"name": "walesonline.co.uk", "seller_id": "17311", "seller_type": "PUBLISHER"}, {"name": "sussexlive.co.uk", "seller_id": "17310", "seller_type": "PUBLISHER"}, {"name": "stokesentinel.co.uk", "seller_id": "17309", "seller_type": "PUBLISHER"}, {"name": "staffordshire-live.co.uk", "seller_id": "17308", "seller_type": "PUBLISHER"}, {"name": "somersetlive.co.uk", "seller_id": "17307", "seller_type": "PUBLISHER"}, {"name": "rsvplive.ie", "seller_id": "17306", "seller_type": "PUBLISHER"}, {"name": "plymouthherald.co.uk", "seller_id": "17305", "seller_type": "PUBLISHER"}, {"name": "ok.co.uk", "seller_id": "17304", "seller_type": "PUBLISHER"}, {"name": "nottinghampost.com", "seller_id": "17303", "seller_type": "PUBLISHER"}, {"name": "northantslive.news", "seller_id": "17302", "seller_type": "PUBLISHER"}, {"name": "mylondon.news", "seller_id": "17301", "seller_type": "PUBLISHER"}, {"name": "manchestereveningnews.co.uk", "seller_id": "17300", "seller_type": "PUBLISHER"}, {"name": "liverpoolecho.co.uk", "seller_id": "17299", "seller_type": "PUBLISHER"}, {"name": "liverpool.com", "seller_id": "17298", "seller_type": "PUBLISHER"}, {"name": "lincolnshirelive.co.uk", "seller_id": "17297", "seller_type": "PUBLISHER"}, {"name": "leicestermercury.co.uk", "seller_id": "17296", "seller_type": "PUBLISHER"}, {"name": "leeds-live.co.uk", "seller_id": "17295", "seller_type": "PUBLISHER"}, {"name": "lancs.live", "seller_id": "17294", "seller_type": "PUBLISHER"}, {"name": "kentlive.news", "seller_id": "17293", "seller_type": "PUBLISHER"}, {"name": "irishmirror.ie", "seller_id": "17292", "seller_type": "PUBLISHER"}, {"name": "hulldailymail.co.uk", "seller_id": "17291", "seller_type": "PUBLISHER"}, {"name": "hertfordshiremercury.co.uk", "seller_id": "17290", "seller_type": "PUBLISHER"}, {"name": "hampshirelive.news", "seller_id": "17289", "seller_type": "PUBLISHER"}, {"name": "grimsbytelegraph.co.uk", "seller_id": "17288", "seller_type": "PUBLISHER"}, {"name": "gloucestershirelive.co.uk", "seller_id": "17287", "seller_type": "PUBLISHER"}, {"name": "glasgowlive.co.uk", "seller_id": "17286", "seller_type": "PUBLISHER"}, {"name": "getsurrey.co.uk", "seller_id": "17285", "seller_type": "PUBLISHER"}, {"name": "getreading.co.uk", "seller_id": "17284", "seller_type": "PUBLISHER"}, {"name": "gazettelive.co.uk", "seller_id": "17283", "seller_type": "PUBLISHER"}, {"name": "football.london", "seller_id": "17282", "seller_type": "PUBLISHER"}, {"name": "examinerlive.co.uk", "seller_id": "17281", "seller_type": "PUBLISHER"}, {"name": "essexlive.news", "seller_id": "17280", "seller_type": "PUBLISHER"}, {"name": "edinburghlive.co.uk", "seller_id": "17279", "seller_type": "PUBLISHER"}, {"name": "dublinlive.ie", "seller_id": "17278", "seller_type": "PUBLISHER"}, {"name": "devonlive.com", "seller_id": "17277", "seller_type": "PUBLISHER"}, {"name": "derbytelegraph.co.uk", "seller_id": "17276", "seller_type": "PUBLISHER"}, {"name": "dailystar.co.uk", "seller_id": "17275", "seller_type": "PUBLISHER"}, {"name": "dailyrecord.co.uk", "seller_id": "17274", "seller_type": "PUBLISHER"}, {"name": "dailypost.co.uk", "seller_id": "17273", "seller_type": "PUBLISHER"}, {"name": "coventrytelegraph.net", "seller_id": "17272", "seller_type": "PUBLISHER"}, {"name": "cornwalllive.com", "seller_id": "17271", "seller_type": "PUBLISHER"}, {"name": "corkbeo.ie", "seller_id": "17270", "seller_type": "PUBLISHER"}, {"name": "chroniclelive.co.uk", "seller_id": "17269", "seller_type": "PUBLISHER"}, {"name": "chesire-live.co.uk", "seller_id": "17268", "seller_type": "PUBLISHER"}, {"name": "chesire-live.co.uk", "seller_id": "17267", "seller_type": "PUBLISHER"}, {"name": "cambridge-news.co.uk", "seller_id": "17266", "seller_type": "PUBLISHER"}, {"name": "buzz.ie", "seller_id": "17265", "seller_type": "PUBLISHER"}, {"name": "business-live.co.uk", "seller_id": "17264", "seller_type": "PUBLISHER"}, {"name": "buckinghamshirelive.com", "seller_id": "17263", "seller_type": "PUBLISHER"}, {"name": "bristolpost.co.uk", "seller_id": "17262", "seller_type": "PUBLISHER"}, {"name": "birminghammail.co.uk", "seller_id": "17261", "seller_type": "PUBLISHER"}, {"name": "belfastlive.co.uk", "seller_id": "17260", "seller_type": "PUBLISHER"}, {"name": "bedfordshirelive.co.uk", "seller_id": "17259", "seller_type": "PUBLISHER"}, {"name": "novi1.ba", "seller_id": "17258", "seller_type": "PUBLISHER"}, {"name": "novi.ba", "seller_id": "17256", "seller_type": "PUBLISHER"}, {"name": "jamiedruce.io", "seller_id": "17255", "seller_type": "PUBLISHER"}, {"name": "earth.com", "seller_id": "17254", "seller_type": "PUBLISHER"}, {"name": "tyla.com", "seller_id": "17253", "seller_type": "PUBLISHER"}, {"name": "sportbible.com", "seller_id": "17252", "seller_type": "PUBLISHER"}, {"name": "unilad.co.uk", "seller_id": "17251", "seller_type": "PUBLISHER"}, {"name": "gamingbible.co.uk", "seller_id": "17250", "seller_type": "PUBLISHER"}, {"name": "ladbible.com", "seller_id": "17249", "seller_type": "PUBLISHER"}, {"name": "whatcar.com", "seller_id": "17248", "seller_type": "PUBLISHER"}, {"name": "classicandsportscar.com", "seller_id": "17247", "seller_type": "PUBLISHER"}, {"name": "autocar.co.uk", "seller_id": "17246", "seller_type": "PUBLISHER"}, {"name": "onbuy.com", "seller_id": "17245", "seller_type": "PUBLISHER"}, {"name": "iwcomps.com", "seller_id": "17244", "seller_type": "PUBLISHER"}, {"name": "keswickreminder.co.uk", "seller_id": "17243", "seller_type": "PUBLISHER"}, {"name": "cumbriacrack.com", "seller_id": "17241", "seller_type": "PUBLISHER"}, {"name": "cwherald.com", "seller_id": "17240", "seller_type": "PUBLISHER"}, {"name": "dailyecho.co.uk", "seller_id": "17239", "seller_type": "PUBLISHER"}, {"name": "exchangeandmart.co.uk", "seller_id": "17238", "seller_type": "PUBLISHER"}, {"name": "bicesteradvertiser.net", "seller_id": "17237", "seller_type": "PUBLISHER"}, {"name": "stage.bocalista.com", "seller_id": "17236", "seller_type": "PUBLISHER"}, {"name": "nationalrail.co.uk", "seller_id": "17235", "seller_type": "PUBLISHER"}, {"name": "espncricinfo.com", "seller_id": "17233", "seller_type": "PUBLISHER"}, {"name": "standard.co.uk", "seller_id": "17232", "seller_type": "PUBLISHER"}, {"name": "visordown.com", "seller_id": "17231", "seller_type": "PUBLISHER"}, {"name": "crash.net", "seller_id": "17230", "seller_type": "PUBLISHER"}, {"name": "relogi.com", "seller_id": "17229", "seller_type": "PUBLISHER"}, {"name": "relogi.com", "seller_id": "17228", "seller_type": "PUBLISHER"}, {"name": "relogi.com", "seller_id": "17227", "seller_type": "PUBLISHER"}, {"name": "dewobroto.my.id", "seller_id": "17226", "seller_type": "PUBLISHER"}, {"name": "westword.com", "seller_id": "17225", "seller_type": "PUBLISHER"}, {"name": "autoscout24.com", "seller_id": "17224", "seller_type": "PUBLISHER"}, {"name": "Granniesjokes.com", "seller_id": "17223", "seller_type": "PUBLISHER"}, {"name": "Funnygrannies.com", "seller_id": "17222", "seller_type": "PUBLISHER"}, {"name": "tv.taghtia.com", "seller_id": "17221", "seller_type": "PUBLISHER"}, {"name": "mgevs.com", "seller_id": "17220", "seller_type": "PUBLISHER"}, {"name": "course-profile.hole19golf.com", "seller_id": "17219", "seller_type": "PUBLISHER"}, {"name": "jpost.com", "seller_id": "17211", "seller_type": "PUBLISHER"}, {"name": "goldradiouk.com", "seller_id": "17210", "seller_type": "PUBLISHER"}, {"name": "golfmagic.com", "seller_id": "17209", "seller_type": "PUBLISHER"}, {"name": "khaosod.co.th", "seller_id": "17208", "seller_type": "PUBLISHER"}, {"name": "khaosod.co.th", "seller_id": "17207", "seller_type": "PUBLISHER"}, {"name": "nownews.com", "seller_id": "17206", "seller_type": "PUBLISHER"}, {"name": "goreadfootball.com", "seller_id": "17198", "seller_type": "PUBLISHER"}, {"name": "goreadtech.com", "seller_id": "17197", "seller_type": "PUBLISHER"}, {"name": "goreadproperty.com", "seller_id": "17196", "seller_type": "PUBLISHER"}, {"name": "goreadlifestyle.com", "seller_id": "17195", "seller_type": "PUBLISHER"}, {"name": "goreadhealth.com", "seller_id": "17194", "seller_type": "PUBLISHER"}, {"name": "goreaddaily.com", "seller_id": "17193", "seller_type": "PUBLISHER"}, {"name": "goreadfinance.com", "seller_id": "17191", "seller_type": "PUBLISHER"}, {"name": "goreadbusiness.com", "seller_id": "17190", "seller_type": "PUBLISHER"}, {"name": "goreadtravel.com", "seller_id": "17189", "seller_type": "PUBLISHER"}, {"name": "thetrainline.com", "seller_id": "17188", "seller_type": "PUBLISHER"}, {"name": "officialcharts.com", "seller_id": "17187", "seller_type": "PUBLISHER"}, {"name": "desperateseller.co.uk", "seller_id": "17185", "seller_type": "PUBLISHER"}, {"name": "guidedofus.com", "seller_id": "17184", "seller_type": "PUBLISHER"}, {"name": "myweather2.com", "seller_id": "17180", "seller_type": "PUBLISHER"}, {"name": "kitbag.com", "seller_id": "17178", "seller_type": "PUBLISHER"}, {"name": "fanatics.com", "seller_id": "17177", "seller_type": "PUBLISHER"}, {"name": "mygoldmusic.co.uk", "seller_id": "17173", "seller_type": "PUBLISHER"}, {"name": "lbc.co.uk", "seller_id": "17172", "seller_type": "PUBLISHER"}, {"name": "capitaldance.com", "seller_id": "17171", "seller_type": "PUBLISHER"}, {"name": "radiox.co.uk", "seller_id": "17170", "seller_type": "PUBLISHER"}, {"name": "classicfm.com", "seller_id": "17169", "seller_type": "PUBLISHER"}, {"name": "capitalxtra.com", "seller_id": "17168", "seller_type": "PUBLISHER"}, {"name": "smoothradio.com", "seller_id": "17167", "seller_type": "PUBLISHER"}, {"name": "popbuzz.com", "seller_id": "17166", "seller_type": "PUBLISHER"}, {"name": "capitalfm.com", "seller_id": "17165", "seller_type": "PUBLISHER"}, {"name": "archant.co.uk", "seller_id": "17164", "seller_type": "PUBLISHER"}, {"name": "rts36.com", "seller_id": "17163", "seller_type": "PUBLISHER"}, {"name": "dirtbikerider.com", "seller_id": "17162", "seller_type": "PUBLISHER"}, {"name": "dirtbikerider.com", "seller_id": "17161", "seller_type": "PUBLISHER"}, {"name": "thevalue101.com", "seller_id": "17160", "seller_type": "PUBLISHER"}, {"name": "thevalue101.com", "seller_id": "17159", "seller_type": "PUBLISHER"}, {"name": "1492058.Suara.Com", "seller_id": "17158", "seller_type": "PUBLISHER"}, {"name": "1492062.matamata.com", "seller_id": "17157", "seller_type": "PUBLISHER"}, {"name": "HiTekno.com", "seller_id": "17156", "seller_type": "PUBLISHER"}, {"name": "BolaTimes.com", "seller_id": "17155", "seller_type": "PUBLISHER"}, {"name": "himedik.com", "seller_id": "17154", "seller_type": "PUBLISHER"}, {"name": "Mobimoto.com", "seller_id": "17153", "seller_type": "PUBLISHER"}, {"name": "tvguide.co.uk", "seller_id": "17152", "seller_type": "PUBLISHER"}, {"name": "jpimedia.co.uk", "seller_id": "17151", "seller_type": "PUBLISHER"}, {"name": "jpimedia.co.uk", "seller_id": "17150", "seller_type": "PUBLISHER"}, {"name": "manadopost.jawapos.com", "seller_id": "17149", "seller_type": "PUBLISHER"}, {"name": "manadopost.jawapos.com", "seller_id": "17148", "seller_type": "PUBLISHER"}, {"name": "radargresik.jawapos.com", "seller_id": "17147", "seller_type": "PUBLISHER"}, {"name": "radarsidoarjo.jawapos.com", "seller_id": "17146", "seller_type": "PUBLISHER"}, {"name": "hellomagazine.com", "seller_id": "17143", "seller_type": "PUBLISHER"}, {"name": "express.co.uk", "seller_id": "17142", "seller_type": "PUBLISHER"}, {"name": "mirror.co.uk", "seller_id": "17141", "seller_type": "PUBLISHER"}, {"name": "trustedreviews.com", "seller_id": "17139", "seller_type": "PUBLISHER"}, {"name": "foodnetwork.co.uk", "seller_id": "17137", "seller_type": "PUBLISHER"}, {"name": "eurosport.co.uk", "seller_id": "17135", "seller_type": "PUBLISHER"}, {"name": "discoveryuk.com", "seller_id": "17134", "seller_type": "PUBLISHER"}, {"name": "lab.fm", "seller_id": "17132", "seller_type": "PUBLISHER"}, {"name": "guitar.com", "seller_id": "17131", "seller_type": "PUBLISHER"}, {"name": "musictech.net", "seller_id": "17130", "seller_type": "PUBLISHER"}, {"name": "uncut.co.uk", "seller_id": "17129", "seller_type": "PUBLISHER"}, {"name": "nme.com", "seller_id": "17128", "seller_type": "PUBLISHER"}, {"name": "interstitial.myweather.com", "seller_id": "17126", "seller_type": "PUBLISHER"}, {"name": "indosport.com", "seller_id": "17125", "seller_type": "PUBLISHER"}, {"name": "goreadauto.com", "seller_id": "17124", "seller_type": "PUBLISHER"}, {"name": "heart.co.uk", "seller_id": "17123", "seller_type": "PUBLISHER"}, {"name": "sofascore.com", "seller_id": "17122", "seller_type": "PUBLISHER"}, {"name": "theweek.co.uk", "seller_id": "17117", "seller_type": "PUBLISHER"}, {"name": "moneyweek.com", "seller_id": "17116", "seller_type": "PUBLISHER"}, {"name": "kiplinger.com", "seller_id": "17114", "seller_type": "PUBLISHER"}, {"name": "itpro.co.uk", "seller_id": "17113", "seller_type": "PUBLISHER"}, {"name": "evo.co.uk", "seller_id": "17112", "seller_type": "PUBLISHER"}, {"name": "drivingelectric.com", "seller_id": "17111", "seller_type": "PUBLISHER"}, {"name": "cyclist.co.uk", "seller_id": "17110", "seller_type": "PUBLISHER"}, {"name": "cloudpro.co.uk", "seller_id": "17109", "seller_type": "PUBLISHER"}, {"name": "channelpro.co.uk", "seller_id": "17108", "seller_type": "PUBLISHER"}, {"name": "carbuyer.co.uk", "seller_id": "17107", "seller_type": "PUBLISHER"}, {"name": "carthrottle.com", "seller_id": "17106", "seller_type": "PUBLISHER"}, {"name": "buyacar.co.uk", "seller_id": "17105", "seller_type": "PUBLISHER"}, {"name": "autoexpress.co.uk", "seller_id": "17104", "seller_type": "PUBLISHER"}, {"name": "Otosia.com", "seller_id": "17102", "seller_type": "PUBLISHER"}, {"name": "Bola.net", "seller_id": "17101", "seller_type": "PUBLISHER"}, {"name": "Merdeka.com", "seller_id": "17100", "seller_type": "PUBLISHER"}, {"name": "Kapanlagi.com", "seller_id": "17099", "seller_type": "PUBLISHER"}, {"name": "Bola.com", "seller_id": "17098", "seller_type": "PUBLISHER"}, {"name": "Liputan6.com", "seller_id": "17097", "seller_type": "PUBLISHER"}, {"name": "dailysportscar.com", "seller_id": "17094", "seller_type": "PUBLISHER"}, {"name": "worldsoccer.com", "seller_id": "17093", "seller_type": "PUBLISHER"}, {"name": "truckingmag.co.uk", "seller_id": "17092", "seller_type": "PUBLISHER"}, {"name": "transportcafe.co.uk", "seller_id": "17091", "seller_type": "PUBLISHER"}, {"name": "oldglory.co.uk", "seller_id": "17090", "seller_type": "PUBLISHER"}, {"name": "heritagemachines.com", "seller_id": "17089", "seller_type": "PUBLISHER"}, {"name": "amateurphotographer.co.uk", "seller_id": "17088", "seller_type": "PUBLISHER"}, {"name": "coachmag.co.uk", "seller_id": "17087", "seller_type": "PUBLISHER"}, {"name": "expertreviews.co.uk", "seller_id": "17086", "seller_type": "PUBLISHER"}, {"name": "radartasikmalaya.com", "seller_id": "17083", "seller_type": "PUBLISHER"}, {"name": "vtv.com.hn", "seller_id": "17082", "seller_type": "PUBLISHER"}, {"name": "tn23.tv", "seller_id": "17081", "seller_type": "PUBLISHER"}, {"name": "chapinradio.com", "seller_id": "17080", "seller_type": "PUBLISHER"}, {"name": "nicaradios.com.ni", "seller_id": "17079", "seller_type": "PUBLISHER"}, {"name": "canal12.com.sv", "seller_id": "17077", "seller_type": "PUBLISHER"}, {"name": "guruhitech.com", "seller_id": "17076", "seller_type": "PUBLISHER"}, {"name": "hawtcelebs.com", "seller_id": "17073", "seller_type": "PUBLISHER"}, {"name": "dirtbikerider.com", "seller_id": "17072", "seller_type": "PUBLISHER"}, {"name": "stats-2.hole19golf.com", "seller_id": "17070", "seller_type": "PUBLISHER"}, {"name": "stats-1.hole19golf.com", "seller_id": "17069", "seller_type": "PUBLISHER"}, {"name": "rounds-list.hole19golf.com", "seller_id": "17068", "seller_type": "PUBLISHER"}, {"name": "round-summary.hole19golf.com", "seller_id": "17067", "seller_type": "PUBLISHER"}, {"name": "mid-round-4.hole19golf.com", "seller_id": "17065", "seller_type": "PUBLISHER"}, {"name": "mid-round-3.hole19golf.com", "seller_id": "17064", "seller_type": "PUBLISHER"}, {"name": "mid-round-2.hole19golf.com", "seller_id": "17063", "seller_type": "PUBLISHER"}, {"name": "mid-round-1.hole19golf.com", "seller_id": "17062", "seller_type": "PUBLISHER"}, {"name": "feed-5.hole19golf.com", "seller_id": "17061", "seller_type": "PUBLISHER"}, {"name": "feed-4.hole19golf.com", "seller_id": "17060", "seller_type": "PUBLISHER"}, {"name": "feed-3.hole19golf.com", "seller_id": "17059", "seller_type": "PUBLISHER"}, {"name": "feed-2.hole19golf.com", "seller_id": "17058", "seller_type": "PUBLISHER"}, {"name": "feed-1.hole19golf.com", "seller_id": "17057", "seller_type": "PUBLISHER"}, {"name": "discovery-3.hole19golf.com", "seller_id": "17056", "seller_type": "PUBLISHER"}, {"name": "discovery-2.hole19golf.com", "seller_id": "17055", "seller_type": "PUBLISHER"}, {"name": "discovery-1.hole19golf.com", "seller_id": "17054", "seller_type": "PUBLISHER"}, {"name": "antena7.com.do", "seller_id": "17053", "seller_type": "PUBLISHER"}, {"name": "antena7.com.do", "seller_id": "17052", "seller_type": "PUBLISHER"}, {"name": "bikesportnews.com", "seller_id": "17050", "seller_type": "PUBLISHER"}, {"name": "abqjournal.com", "seller_id": "17049", "seller_type": "PUBLISHER"}, {"name": "uniqpaid.com", "seller_id": "17047", "seller_type": "PUBLISHER"}, {"name": "driverdb.com", "seller_id": "17046", "seller_type": "PUBLISHER"}, {"name": "jawapos.com", "seller_id": "17045", "seller_type": "PUBLISHER"}, {"name": "m.jawapos.com", "seller_id": "17044", "seller_type": "PUBLISHER"}, {"name": "radarsemarang.jawapos.com", "seller_id": "17042", "seller_type": "PUBLISHER"}, {"name": "tvc.com.ec", "seller_id": "17039", "seller_type": "PUBLISHER"}, {"name": "rts.com.ec", "seller_id": "17038", "seller_type": "PUBLISHER"}, {"name": "radarsemarang.jawapos.com", "seller_id": "17037", "seller_type": "PUBLISHER"}, {"name": "sumedang.pikiran-rakyat.com", "seller_id": "17036", "seller_type": "PUBLISHER"}, {"name": "portalmajalengka.pikiran-rakyat.com", "seller_id": "17035", "seller_type": "PUBLISHER"}, {"name": "portaljember.pikiran-rakyat.com", "seller_id": "17034", "seller_type": "PUBLISHER"}, {"name": "zonajakarta.pikiran-rakyat.com", "seller_id": "17033", "seller_type": "PUBLISHER"}, {"name": "myweather2.com", "seller_id": "17032", "seller_type": "PUBLISHER"}, {"name": "motorsportauctions.com", "seller_id": "17031", "seller_type": "PUBLISHER"}, {"name": "bold.dk", "seller_id": "17030", "seller_type": "PUBLISHER"}, {"name": "c9n.com.py", "seller_id": "17029", "seller_type": "PUBLISHER"}, {"name": "snt.com.py", "seller_id": "17028", "seller_type": "PUBLISHER"}, {"name": "theclinic.cl", "seller_id": "17027", "seller_type": "PUBLISHER"}, {"name": "myweather2.com", "seller_id": "17022", "seller_type": "PUBLISHER"}, {"name": "bikesportnews.com", "seller_id": "17021", "seller_type": "PUBLISHER"}, {"name": "bikesportnews.com", "seller_id": "17020", "seller_type": "PUBLISHER"}, {"name": "wtf1.com", "seller_id": "17017", "seller_type": "PUBLISHER"}, {"name": "the-race.com", "seller_id": "17016", "seller_type": "PUBLISHER"}, {"name": "happyhealthyandwell.com", "seller_id": "17013", "seller_type": "PUBLISHER"}, {"name": "canal10.com.ni", "seller_id": "17012", "seller_type": "PUBLISHER"}, {"name": "redbolivision.tv.bo", "seller_id": "17011", "seller_type": "PUBLISHER"}, {"name": "chapintv.com", "seller_id": "17010", "seller_type": "PUBLISHER"}, {"name": "repretel.com", "seller_id": "17009", "seller_type": "PUBLISHER"}, {"name": "abqjournal.com", "seller_id": "17008", "seller_type": "PUBLISHER"}, {"name": "abqjournal.com", "seller_id": "17006", "seller_type": "PUBLISHER"}, {"name": "atv.pe", "seller_id": "17003", "seller_type": "PUBLISHER"}, {"name": "atv.pe", "seller_id": "17002", "seller_type": "PUBLISHER"}, {"name": "ayayay.tv", "seller_id": "17001", "seller_type": "PUBLISHER"}, {"name": "1480075.beritadiy.pikiran-rakyat.com", "seller_id": "16998", "seller_type": "PUBLISHER"}, {"name": "1479966.mediablitar.pikiran-rakyat.com", "seller_id": "16997", "seller_type": "PUBLISHER"}, {"name": "thecarexpert.co.uk", "seller_id": "16996", "seller_type": "PUBLISHER"}, {"name": "1478446.historia.id", "seller_id": "16992", "seller_type": "PUBLISHER"}, {"name": "1478444.Womantalk.com", "seller_id": "16991", "seller_type": "PUBLISHER"}, {"name": "1478442.Bolalob.com", "seller_id": "16990", "seller_type": "PUBLISHER"}, {"name": "1478439.Opini.id", "seller_id": "16989", "seller_type": "PUBLISHER"}, {"name": "1478460.jurnaltrip.pikiran-rakyat.com", "seller_id": "16988", "seller_type": "PUBLISHER"}, {"name": "1478411.jakbarnews.pikiran-rakyat.com", "seller_id": "16987", "seller_type": "PUBLISHER"}, {"name": "1478233.semarangku.pikiran-rakyat.com", "seller_id": "16986", "seller_type": "PUBLISHER"}, {"name": "1477552.game.nownews.com", "seller_id": "16973", "seller_type": "PUBLISHER"}, {"name": "1477551.game.nownews.com", "seller_id": "16972", "seller_type": "PUBLISHER"}, {"name": "herobd.com", "seller_id": "16967", "seller_type": "PUBLISHER"}, {"name": "1478076.portallebak.pikiran-rakyat.com", "seller_id": "16966", "seller_type": "PUBLISHER"}, {"name": "1477767.ringtimesbali.pikiran-rakyat.com", "seller_id": "16965", "seller_type": "PUBLISHER"}, {"name": "1477573.portalsurabaya.pikiran-rakyat.com", "seller_id": "16964", "seller_type": "PUBLISHER"}, {"name": "1477436.warnamediabali.pikiran-rakyat.com", "seller_id": "16963", "seller_type": "PUBLISHER"}, {"name": "1477374.portaljogja.pikiran-rakyat.com", "seller_id": "16962", "seller_type": "PUBLISHER"}, {"name": "1477266.lensabanyumas.pikiran-rakyat.com", "seller_id": "16961", "seller_type": "PUBLISHER"}, {"name": "1477230.jurnalpresisi.pikiran-rakyat.com", "seller_id": "16960", "seller_type": "PUBLISHER"}, {"name": "1476885.bekasi.pikiran-rakyat.com", "seller_id": "16959", "seller_type": "PUBLISHER"}, {"name": "1476846.pangandaran.pikiran-rakyat.com", "seller_id": "16958", "seller_type": "PUBLISHER"}, {"name": "1476074.karawang.pikiran-rakyat.com", "seller_id": "16957", "seller_type": "PUBLISHER"}, {"name": "1476072.karawang.pikiran-rakyat.com", "seller_id": "16956", "seller_type": "PUBLISHER"}, {"name": "1476064.cianjur.pikiran-rakyat.com", "seller_id": "16955", "seller_type": "PUBLISHER"}, {"name": "1476062.cianjur.pikiran-rakyat.com", "seller_id": "16954", "seller_type": "PUBLISHER"}, {"name": "1475887.sukabumi.pikiran-rakyat.com", "seller_id": "16953", "seller_type": "PUBLISHER"}, {"name": "1475885.sukabumi.pikiran-rakyat.com", "seller_id": "16952", "seller_type": "PUBLISHER"}, {"name": "1475879.bogor.pikiran-rakyat.com", "seller_id": "16949", "seller_type": "PUBLISHER"}, {"name": "1475877.bogor.pikiran-rakyat.com", "seller_id": "16948", "seller_type": "PUBLISHER"}, {"name": "1475745.lensapurbalingga.pikiran-rakyat.com", "seller_id": "16947", "seller_type": "PUBLISHER"}, {"name": "1475743.lensapurbalingga.pikiran-rakyat.com", "seller_id": "16946", "seller_type": "PUBLISHER"}, {"name": "1475488.kabarlumajang.pikiran-rakyat.com", "seller_id": "16945", "seller_type": "PUBLISHER"}, {"name": "1475487.kabarlumajang.pikiran-rakyat.com", "seller_id": "16944", "seller_type": "PUBLISHER"}, {"name": "1475381.zonabanten.pikiran-rakyat.com", "seller_id": "16943", "seller_type": "PUBLISHER"}, {"name": "1475379.zonabanten.pikiran-rakyat.com", "seller_id": "16942", "seller_type": "PUBLISHER"}, {"name": "1475311.mediapakuan.pikiran-rakyat.com", "seller_id": "16941", "seller_type": "PUBLISHER"}, {"name": "1475308.mediapakuan.pikiran-rakyat.com", "seller_id": "16940", "seller_type": "PUBLISHER"}, {"name": "1475260.mantrasukabumi.pikiran-rakyat.com", "seller_id": "16939", "seller_type": "PUBLISHER"}, {"name": "1475257.mantrasukabumi.pikiran-rakyat.com", "seller_id": "16938", "seller_type": "PUBLISHER"}, {"name": "1475179.jurnalgarut.pikiran-rakyat.com", "seller_id": "16937", "seller_type": "PUBLISHER"}, {"name": "1475177.jurnalgarut.pikiran-rakyat.com", "seller_id": "16936", "seller_type": "PUBLISHER"}, {"name": "1475164.blogunik.com", "seller_id": "16935", "seller_type": "PUBLISHER"}, {"name": "1475162.blogunik.com", "seller_id": "16934", "seller_type": "PUBLISHER"}, {"name": "1475153.galamedia.pikiran-rakyat.com", "seller_id": "16933", "seller_type": "PUBLISHER"}, {"name": "1475148.galamedia.pikiran-rakyat.com", "seller_id": "16932", "seller_type": "PUBLISHER"}, {"name": "1473910.pikiran-rakyat.com", "seller_id": "16931", "seller_type": "PUBLISHER"}, {"name": "1473908.pikiran-rakyat.com", "seller_id": "16930", "seller_type": "PUBLISHER"}, {"name": "1474585.hitekno.com", "seller_id": "16929", "seller_type": "PUBLISHER"}, {"name": "1474582.hitekno.com", "seller_id": "16928", "seller_type": "PUBLISHER"}, {"name": "1477761.m.nownews.com", "seller_id": "16927", "seller_type": "PUBLISHER"}, {"name": "1477758.nownews.com", "seller_id": "16926", "seller_type": "PUBLISHER"}, {"name": "1474576.Himedik.com", "seller_id": "16925", "seller_type": "PUBLISHER"}, {"name": "1474574.m.himedik.com", "seller_id": "16924", "seller_type": "PUBLISHER"}, {"name": "1473633.bolaTimes.com", "seller_id": "16923", "seller_type": "PUBLISHER"}, {"name": "1473630.matamata.com", "seller_id": "16922", "seller_type": "PUBLISHER"}, {"name": "1473627.suara.com", "seller_id": "16921", "seller_type": "PUBLISHER"}, {"name": "mediapakuan.pikiran-rakyat.com", "seller_id": "16916", "seller_type": "PUBLISHER"}, {"name": "mantrasukabumi.pikiran-rakyat.com", "seller_id": "16915", "seller_type": "PUBLISHER"}, {"name": "jurnalgarut.pikiran-rakyat.com", "seller_id": "16914", "seller_type": "PUBLISHER"}, {"name": "galamedia.pikiran-rakyat.com", "seller_id": "16913", "seller_type": "PUBLISHER"}, {"name": "okezone.com", "seller_id": "16912", "seller_type": "PUBLISHER"}, {"name": "m.4wayvoice.nownews.com", "seller_id": "16910", "seller_type": "PUBLISHER"}, {"name": "4wayvoice.nownews.com", "seller_id": "16909", "seller_type": "PUBLISHER"}, {"name": "m.chinapost.nownews.com", "seller_id": "16908", "seller_type": "PUBLISHER"}, {"name": "chinapost.nownews.com", "seller_id": "16907", "seller_type": "PUBLISHER"}, {"name": "m.bobee.nownews.com", "seller_id": "16906", "seller_type": "PUBLISHER"}, {"name": "bobee.nownews.com", "seller_id": "16905", "seller_type": "PUBLISHER"}, {"name": "m.babyyou.nownews.com", "seller_id": "16904", "seller_type": "PUBLISHER"}, {"name": "babyyou.nownews.com", "seller_id": "16903", "seller_type": "PUBLISHER"}, {"name": "bolatimes.com", "seller_id": "16884", "seller_type": "PUBLISHER"}, {"name": "matamata.com", "seller_id": "16883", "seller_type": "PUBLISHER"}, {"name": "suara.com", "seller_id": "16882", "seller_type": "PUBLISHER"}, {"name": "popmama.com", "seller_id": "16879", "seller_type": "PUBLISHER"}, {"name": "popbela.com", "seller_id": "16878", "seller_type": "PUBLISHER"}, {"name": "idntimes.com", "seller_id": "16877", "seller_type": "PUBLISHER"}, {"name": "208872.guu.vn", "seller_id": "16876", "seller_type": "PUBLISHER"}, {"name": "acmods.net", "seller_id": "16873", "seller_type": "PUBLISHER"}, {"name": "www.sindonews.com", "seller_id": "16860", "seller_type": "PUBLISHER"}, {"name": "m.onepage.nownews.com", "seller_id": "16856", "seller_type": "PUBLISHER"}, {"name": "onepage.nownews.com", "seller_id": "16855", "seller_type": "PUBLISHER"}, {"name": "m.creaders.net", "seller_id": "16839", "seller_type": "PUBLISHER"}, {"name": "creaders.net", "seller_id": "16838", "seller_type": "PUBLISHER"}, {"name": "bnext.com.tw", "seller_id": "16837", "seller_type": "PUBLISHER"}, {"name": "Kul.vn", "seller_id": "16785", "seller_type": "PUBLISHER"}, {"name": "ilmupengetahuanumum.com", "seller_id": "16780", "seller_type": "PUBLISHER"}, {"name": "ilmumanajemenindustri.com", "seller_id": "16779", "seller_type": "PUBLISHER"}, {"name": "teknikelektronika.com", "seller_id": "16778", "seller_type": "PUBLISHER"}, {"name": "lared.cl", "seller_id": "16765", "seller_type": "PUBLISHER"}, {"name": "mobile.nownews.com", "seller_id": "16753", "seller_type": "PUBLISHER"}, {"name": "nownews.com", "seller_id": "16752", "seller_type": "PUBLISHER"}, {"name": "lovestorynet.com", "seller_id": "16751", "seller_type": "PUBLISHER"}, {"name": "clickrnews.com", "seller_id": "16750", "seller_type": "PUBLISHER"}, {"name": "chinaqna.com", "seller_id": "16749", "seller_type": "PUBLISHER"}, {"name": "bomb01.com", "seller_id": "16748", "seller_type": "PUBLISHER"}, {"name": "inews.id", "seller_id": "16743", "seller_type": "PUBLISHER"}, {"name": "inews.id", "seller_id": "16742", "seller_type": "PUBLISHER"}, {"name": "www.scifinow.co.uk", "seller_id": "16727", "seller_type": "PUBLISHER"}, {"name": "abc.com", "seller_id": "16726", "seller_type": "PUBLISHER"}, {"name": "www.kruupdate.com", "seller_id": "16725", "seller_type": "PUBLISHER"}, {"name": "news.seehua.com", "seller_id": "16724", "seller_type": "PUBLISHER"}, {"name": "headsup4u.com", "seller_id": "16723", "seller_type": "PUBLISHER"}, {"name": "detik.com", "seller_id": "16722", "seller_type": "PUBLISHER"}, {"name": "kruupdate.com", "seller_id": "16721", "seller_type": "PUBLISHER"}, {"name": "prachachat.net", "seller_id": "16720", "seller_type": "PUBLISHER"}, {"name": "prachachat.net", "seller_id": "16719", "seller_type": "PUBLISHER"}, {"name": "matichon.co.th", "seller_id": "16718", "seller_type": "PUBLISHER"}, {"name": "matichon.co.th", "seller_id": "16717", "seller_type": "PUBLISHER"}, {"name": "trangptm.blogspot.com", "seller_id": "16713", "seller_type": "PUBLISHER"}, {"name": "trangptm.blogspot.com", "seller_id": "16712", "seller_type": "PUBLISHER"}, {"name": "trangptm.blogspot.com", "seller_id": "16711", "seller_type": "PUBLISHER"}, {"name": "womensfitness.co.uk", "seller_id": "16710", "seller_type": "PUBLISHER"}, {"name": "mediamash.com", "seller_id": "16700", "seller_type": "PUBLISHER"}, {"name": "pollhype.com", "seller_id": "16699", "seller_type": "PUBLISHER"}, {"name": "pollhype.com", "seller_id": "16698", "seller_type": "PUBLISHER"}, {"name": "woahworld.com", "seller_id": "16697", "seller_type": "PUBLISHER"}, {"name": "itnewsdirect.com", "seller_id": "16694", "seller_type": "PUBLISHER"}, {"name": "jamiedruce.io", "seller_id": "16692", "seller_type": "PUBLISHER"}, {"name": "popbabble.com", "seller_id": "16681", "seller_type": "PUBLISHER"}, {"name": "popcaller.com", "seller_id": "16680", "seller_type": "PUBLISHER"}, {"name": "popcaller.com", "seller_id": "16679", "seller_type": "PUBLISHER"}, {"name": "popcaller.com", "seller_id": "16678", "seller_type": "PUBLISHER"}, {"name": "popcaller.com", "seller_id": "16670", "seller_type": "PUBLISHER"}, {"name": "cnnindonesia.com", "seller_id": "16668", "seller_type": "PUBLISHER"}, {"name": "haibunda.com", "seller_id": "16666", "seller_type": "PUBLISHER"}, {"name": "mommything.com", "seller_id": "16664", "seller_type": "PUBLISHER"}, {"name": "thedailyheel.com", "seller_id": "16663", "seller_type": "PUBLISHER"}, {"name": "classicfordmag.co.uk", "seller_id": "16607", "seller_type": "PUBLISHER"}, {"name": "yoursmallholding.com", "seller_id": "16606", "seller_type": "PUBLISHER"}, {"name": "thechristmasmagazine.com", "seller_id": "16605", "seller_type": "PUBLISHER"}, {"name": "matchfootball.co.uk", "seller_id": "16604", "seller_type": "PUBLISHER"}, {"name": "fishingnews.co.uk", "seller_id": "16603", "seller_type": "PUBLISHER"}, {"name": "claycraft.co.uk", "seller_id": "16602", "seller_type": "PUBLISHER"}, {"name": "cageandaviarybirds.co.uk", "seller_id": "16601", "seller_type": "PUBLISHER"}, {"name": "tractormagazine.co.uk", "seller_id": "16600", "seller_type": "PUBLISHER"}, {"name": "miniworld.co.uk", "seller_id": "16599", "seller_type": "PUBLISHER"}, {"name": "goreadsport.com", "seller_id": "16598", "seller_type": "PUBLISHER"}, {"name": "slimfitandhealthy.co.uk", "seller_id": "16597", "seller_type": "PUBLISHER"}, {"name": "boxingnewsonline.net", "seller_id": "16596", "seller_type": "PUBLISHER"}, {"name": "outdoorsradar.com", "seller_id": "16594", "seller_type": "PUBLISHER"}, {"name": "outdoorfitnessandadventure.co.uk", "seller_id": "16593", "seller_type": "PUBLISHER"}, {"name": "mensfitness.co.uk", "seller_id": "16592", "seller_type": "PUBLISHER"}, {"name": "121money.com", "seller_id": "16591", "seller_type": "PUBLISHER"}, {"name": "popbust.com", "seller_id": "16589", "seller_type": "PUBLISHER"}, {"name": "popbust.com", "seller_id": "16588", "seller_type": "PUBLISHER"}, {"name": "popbust.com", "seller_id": "16587", "seller_type": "PUBLISHER"}, {"name": "popbust.com", "seller_id": "16586", "seller_type": "PUBLISHER"}, {"name": "pinchfeed.com", "seller_id": "16583", "seller_type": "PUBLISHER"}, {"name": "pinchfeed.com", "seller_id": "16582", "seller_type": "PUBLISHER"}, {"name": "pinchfeed.com", "seller_id": "16581", "seller_type": "PUBLISHER"}, {"name": "snapsfeed.com", "seller_id": "16580", "seller_type": "PUBLISHER"}, {"name": "snapsfeed.com", "seller_id": "16579", "seller_type": "PUBLISHER"}, {"name": "snapsfeed.com", "seller_id": "16578", "seller_type": "PUBLISHER"}, {"name": "snapsfeed.com", "seller_id": "16577", "seller_type": "PUBLISHER"}, {"name": "pollhype.com", "seller_id": "16570", "seller_type": "PUBLISHER"}, {"name": "pollhype.com", "seller_id": "16569", "seller_type": "PUBLISHER"}, {"name": "pollhype.com", "seller_id": "16568", "seller_type": "PUBLISHER"}, {"name": "thedailyheel.com", "seller_id": "16567", "seller_type": "PUBLISHER"}, {"name": "thedailyheel.com", "seller_id": "16566", "seller_type": "PUBLISHER"}, {"name": "thedailyheel.com", "seller_id": "16565", "seller_type": "PUBLISHER"}, {"name": "funnyjk.com", "seller_id": "16564", "seller_type": "PUBLISHER"}, {"name": "funnyjk.com", "seller_id": "16563", "seller_type": "PUBLISHER"}, {"name": "funnyjk.com", "seller_id": "16562", "seller_type": "PUBLISHER"}, {"name": "woahworld.com", "seller_id": "16561", "seller_type": "PUBLISHER"}, {"name": "woahworld.com", "seller_id": "16560", "seller_type": "PUBLISHER"}, {"name": "woahworld.com", "seller_id": "16559", "seller_type": "PUBLISHER"}, {"name": "stylegoop.com", "seller_id": "16558", "seller_type": "PUBLISHER"}, {"name": "stylegoop.com", "seller_id": "16557", "seller_type": "PUBLISHER"}, {"name": "stylegoop.com", "seller_id": "16556", "seller_type": "PUBLISHER"}, {"name": "mommything.com", "seller_id": "16555", "seller_type": "PUBLISHER"}, {"name": "mommything.com", "seller_id": "16554", "seller_type": "PUBLISHER"}, {"name": "mommything.com", "seller_id": "16553", "seller_type": "PUBLISHER"}, {"name": "dailysovereign.com", "seller_id": "16552", "seller_type": "PUBLISHER"}, {"name": "dailysovereign.com", "seller_id": "16551", "seller_type": "PUBLISHER"}, {"name": "dailysovereign.com", "seller_id": "16550", "seller_type": "PUBLISHER"}, {"name": "woahworld.com", "seller_id": "16522", "seller_type": "PUBLISHER"}, {"name": "avforums.com", "seller_id": "16486", "seller_type": "PUBLISHER"}, {"name": "dailysovereign.com", "seller_id": "16483", "seller_type": "PUBLISHER"}, {"name": "mommything.com", "seller_id": "16482", "seller_type": "PUBLISHER"}, {"name": "dailysovereign.com", "seller_id": "16476", "seller_type": "PUBLISHER"}, {"name": "fordraptor2.com", "seller_id": "16475", "seller_type": "PUBLISHER"}, {"name": "miniclip.com", "seller_id": "16369", "seller_type": "PUBLISHER"}, {"name": "swapz.co.uk", "seller_id": "16363", "seller_type": "PUBLISHER"}, {"name": "classicsworld.co.uk", "seller_id": "16359", "seller_type": "PUBLISHER"}, {"name": "triradar.com", "seller_id": "16358", "seller_type": "PUBLISHER"}, {"name": "runnersradar.com", "seller_id": "16357", "seller_type": "PUBLISHER"}, {"name": "outdoorfitnessmag.com", "seller_id": "16356", "seller_type": "PUBLISHER"}, {"name": "tgomagazine.co.uk", "seller_id": "16355", "seller_type": "PUBLISHER"}, {"name": "holidayhomeliving.co.uk", "seller_id": "16354", "seller_type": "PUBLISHER"}, {"name": "shipsmonthly.com", "seller_id": "16353", "seller_type": "PUBLISHER"}, {"name": "parkhomemagazine.co.uk", "seller_id": "16352", "seller_type": "PUBLISHER"}, {"name": "topsante.co.uk", "seller_id": "16351", "seller_type": "PUBLISHER"}, {"name": "profi.com", "seller_id": "16350", "seller_type": "PUBLISHER"}, {"name": "fastfordmag.co.uk", "seller_id": "16349", "seller_type": "PUBLISHER"}, {"name": "coastmagazine.co.uk", "seller_id": "16348", "seller_type": "PUBLISHER"}, {"name": "fastcar.co.uk", "seller_id": "16347", "seller_type": "PUBLISHER"}, {"name": "psychologies.co.uk", "seller_id": "16346", "seller_type": "PUBLISHER"}, {"name": "stuff.tv", "seller_id": "16345", "seller_type": "PUBLISHER"}, {"name": "stylegoop.com", "seller_id": "16339", "seller_type": "PUBLISHER"}, {"name": "theusawire.com", "seller_id": "16337", "seller_type": "PUBLISHER"}, {"name": "autovillage.co.uk", "seller_id": "16333", "seller_type": "PUBLISHER"}, {"name": "carsite.co.uk", "seller_id": "16332", "seller_type": "PUBLISHER"}, {"name": "friday-ad.co.uk", "seller_id": "16291", "seller_type": "PUBLISHER"}, {"name": "pollhype.com", "seller_id": "16283", "seller_type": "PUBLISHER"}, {"name": "dailysovereign.com", "seller_id": "16253", "seller_type": "PUBLISHER"}, {"name": "jobs.cabincrew.com", "seller_id": "15957", "seller_type": "PUBLISHER"}, {"name": "careersinrecruitment.com", "seller_id": "15956", "seller_type": "PUBLISHER"}, {"name": "simplyhrjobs.co.uk", "seller_id": "15955", "seller_type": "PUBLISHER"}, {"name": "traveljobsearch.com", "seller_id": "15954", "seller_type": "PUBLISHER"}, {"name": "quiza.me", "seller_id": "15875", "seller_type": "PUBLISHER"}, {"name": "pollhype.com", "seller_id": "15819", "seller_type": "PUBLISHER"}, {"name": "woahworld.com", "seller_id": "15815", "seller_type": "PUBLISHER"}, {"name": "woahworld.com", "seller_id": "15747", "seller_type": "PUBLISHER"}, {"name": "honestjohn.co.uk", "seller_id": "15668", "seller_type": "PUBLISHER"}, {"name": "ventadecaballos.es", "seller_id": "15553", "seller_type": "PUBLISHER"}, {"name": "traveljobs.com", "seller_id": "15549", "seller_type": "PUBLISHER"}, {"name": "simplysalesjobs.co.uk", "seller_id": "15548", "seller_type": "PUBLISHER"}, {"name": "simplymarketingjobs.co.uk", "seller_id": "15547", "seller_type": "PUBLISHER"}, {"name": "simplylawjobs.com", "seller_id": "15546", "seller_type": "PUBLISHER"}, {"name": "simplyhoteljobs.com", "seller_id": "15545", "seller_type": "PUBLISHER"}, {"name": "simplyengineeringjobs.com", "seller_id": "15544", "seller_type": "PUBLISHER"}, {"name": "jobs.natives.co.uk", "seller_id": "15543", "seller_type": "PUBLISHER"}, {"name": "kittenads.co.uk", "seller_id": "15542", "seller_type": "PUBLISHER"}, {"name": "inautomotive.com", "seller_id": "15541", "seller_type": "PUBLISHER"}, {"name": "farmingads.co.uk", "seller_id": "15540", "seller_type": "PUBLISHER"}, {"name": "cabincrew.com", "seller_id": "15539", "seller_type": "PUBLISHER"}, {"name": "aviationjobsearch.com", "seller_id": "15538", "seller_type": "PUBLISHER"}, {"name": "aviationjobsearch.com", "seller_id": "15537", "seller_type": "PUBLISHER"}, {"name": "gunstar.co.uk", "seller_id": "15517", "seller_type": "PUBLISHER"}, {"name": "birdtrader.co.uk", "seller_id": "15401", "seller_type": "PUBLISHER"}, {"name": "caravansforsale.co.uk", "seller_id": "15399", "seller_type": "PUBLISHER"}, {"name": "horseclicks.com", "seller_id": "15397", "seller_type": "PUBLISHER"}, {"name": "friday-ad.co.uk", "seller_id": "15394", "seller_type": "PUBLISHER"}, {"name": "friday-ad.co.uk", "seller_id": "15393", "seller_type": "PUBLISHER"}, {"name": "dogsandpuppies.co.uk", "seller_id": "15379", "seller_type": "PUBLISHER"}, {"name": "horsemart.co.uk", "seller_id": "15378", "seller_type": "PUBLISHER"}, {"name": "boatsandoutboards.co.uk", "seller_id": "15377", "seller_type": "PUBLISHER"}, {"name": "boatshop24.com", "seller_id": "15376", "seller_type": "PUBLISHER"}, {"name": "boatshop24.co.uk", "seller_id": "15375", "seller_type": "PUBLISHER"}, {"name": "wightbay.com", "seller_id": "15374", "seller_type": "PUBLISHER"}, {"name": "thedailyheel.com", "seller_id": "15370", "seller_type": "PUBLISHER"}, {"name": "mommything.com", "seller_id": "15369", "seller_type": "PUBLISHER"}, {"name": "friday-ad.co.uk", "seller_id": "15352", "seller_type": "PUBLISHER"}, {"name": "dogsandpuppies.co.uk", "seller_id": "15346", "seller_type": "PUBLISHER"}, {"name": "horsemart.co.uk", "seller_id": "15345", "seller_type": "PUBLISHER"}, {"name": "thedailyheel.com", "seller_id": "15282", "seller_type": "PUBLISHER"}, {"name": "funnyjk.com", "seller_id": "15022", "seller_type": "PUBLISHER"}, {"name": "stylegoop.com", "seller_id": "15020", "seller_type": "PUBLISHER"}, {"name": "bocalista.com", "seller_id": "14797", "seller_type": "PUBLISHER"}, {"name": "woahworld.com", "seller_id": "14590", "seller_type": "PUBLISHER"}, {"name": "pollhype.com", "seller_id": "14588", "seller_type": "PUBLISHER"}, {"name": "thedailyheel.com", "seller_id": "14587", "seller_type": "PUBLISHER"}, {"name": "mommything.com", "seller_id": "14586", "seller_type": "PUBLISHER"}, {"name": "popbabble.com", "seller_id": "14209", "seller_type": "PUBLISHER"}]}