{"contact_address": "Yieldlab AG, Colonnaden 41, 20354 Hamburg, Germany", "version": "1.0", "contact_email": "support@yieldlab.de", "sellers": [{"seller_id": "129064", "name": "Foundea GmbH", "seller_type": "PUBLISHER", "domain": "foundea.de"}, {"seller_id": "91034", "name": "Greven Medien GmbH & Co. KG", "seller_type": "PUBLISHER", "domain": "greven.de"}, {"seller_id": "7103487", "name": "highfivve GmbH", "seller_type": "BOTH", "domain": "highfivve.com"}, {"seller_id": "62715", "name": "Immowelt AG", "seller_type": "PUBLISHER", "domain": "immowelt.de"}, {"seller_id": "89180", "name": "Yieldlab AG", "seller_type": "PUBLISHER", "domain": "yieldlab.de"}, {"seller_id": "70", "name": "Reachnet DE Ltd.", "seller_type": "INTERMEDIARY", "domain": "reachnet.de"}, {"seller_id": "453131", "name": "Media Impact GmbH & Co. KG", "seller_type": "PUBLISHER", "domain": "mediaimpact.de"}, {"seller_id": "72723", "name": "ProSiebenSat.1 PULS 4 GmbH", "seller_type": "PUBLISHER", "domain": "prosiebensat1puls4.com"}, {"seller_id": "21691", "name": "BurdaForward Advertising GmbH", "seller_type": "PUBLISHER", "domain": "burda-forward.de"}, {"seller_id": "11795", "name": "Mobile.de GmbH", "seller_type": "PUBLISHER", "domain": "mobile.de"}, {"seller_id": "13216", "name": "United Internet Media GmbH", "seller_type": "BOTH", "domain": "united-internet-media.de"}, {"seller_id": "11114007", "name": "Apester Ltd.", "seller_type": "INTERMEDIARY", "domain": "apester.com"}, {"seller_id": "46035", "name": "Lablue", "seller_type": "PUBLISHER", "domain": "lablue.de"}, {"seller_id": "11124744", "name": "Click Performance GmbH", "seller_type": "INTERMEDIARY", "domain": "click-performance.com"}, {"seller_id": "35673", "name": "Advertising Alliance", "seller_type": "INTERMEDIARY", "domain": "advertising-alliance.de"}, {"seller_id": "11132397", "name": "Deutscher Fachverlag", "seller_type": "PUBLISHER", "domain": "dfv.de"}, {"seller_id": "227473", "name": "STANDARD Verlagsgesellschaft m.b.H", "seller_type": "PUBLISHER", "domain": "derstandard.at"}, {"seller_id": "161633", "name": "Wohnnet Medien GmbH", "seller_type": "PUBLISHER", "domain": "wohnnet.at"}, {"seller_id": "163835", "name": "tisoomi GmbH", "seller_type": "INTERMEDIARY", "domain": "tisoomi.de"}, {"seller_id": "6378054", "name": "ShowHeroes SE", "seller_type": "BOTH", "domain": "showheroes.com"}, {"seller_id": "227224", "name": "Yieldlab Premium Network", "seller_type": "INTERMEDIARY", "domain": "yieldlab.de"}, {"seller_id": "11132508", "name": "MTB-News \u2013 Thomas Paatz", "seller_type": "PUBLISHER", "domain": "mtb-news.de"}, {"seller_id": "5710", "name": "SevenOne Media GmbH", "seller_type": "BOTH", "domain": "sevenonemedia.de"}, {"seller_id": "804180", "name": "Verivox GmbH", "seller_type": "PUBLISHER", "domain": "verivox.com"}, {"seller_id": "402360", "name": "GCM Go City Media GmbH", "seller_type": "PUBLISHER", "domain": "gcmberlin.de"}, {"seller_id": "47883", "name": "playzo GmbH", "seller_type": "PUBLISHER", "domain": "playzo.de"}, {"seller_id": "348727", "name": "Exaring AG", "seller_type": "PUBLISHER", "domain": "waipu.tv"}, {"seller_id": "342882", "name": "mov.ad GmbH", "seller_type": "PUBLISHER", "domain": "adition.de"}, {"seller_id": "2172218", "name": "SMARTSTREAM.TV GmbH", "seller_type": "BOTH", "domain": "smartstream.tv"}, {"seller_id": "495507", "name": "Netpoint Media GmbH", "seller_type": "INTERMEDIARY", "domain": "netpoint-media.de"}, {"seller_id": "509981", "name": "Pushfire GmbH", "seller_type": "BOTH", "domain": "pushfire.de"}, {"seller_id": "521617", "name": "theINDUSTRY AG", "seller_type": "INTERMEDIARY", "domain": "theindustry.ch"}, {"seller_id": "506261", "name": "Prex Programmatic Exchange GmbH & Co. KG (YDC)", "seller_type": "INTERMEDIARY", "domain": "serviceplan.com"}, {"seller_id": "411126", "name": "wallstreet:online AG", "seller_type": "PUBLISHER", "domain": "wallstreet-online.de"}, {"seller_id": "411982", "name": "commonMedia GmbH", "seller_type": "INTERMEDIARY", "domain": "commonmedia.de"}, {"seller_id": "11142664", "name": "RND RedaktionsNetzwerk Deutschland GmbH", "seller_type": "PUBLISHER", "domain": "rnd.de"}, {"seller_id": "116373", "name": "Otto Group Media GmbH", "seller_type": "PUBLISHER", "domain": "ottogroup.media"}, {"seller_id": "2223324", "name": "Adopstar", "seller_type": "PUBLISHER", "domain": "adopstar.com"}, {"seller_id": "851872", "name": "PEP SevenOneMedia (YDC)", "seller_type": "BOTH", "domain": "sevenonemedia.de"}, {"seller_id": "939971", "name": "Promiflash", "seller_type": "PUBLISHER", "domain": "promiflash.de"}, {"seller_id": "961276", "name": "mPlatform (YDC)", "seller_type": "INTERMEDIARY", "domain": "groupm.com"}, {"seller_id": "886718", "name": "Define Media GmbH", "seller_type": "BOTH", "domain": "definemedia.de"}, {"seller_id": "2131631", "name": "e-quadrat communications gmbh", "seller_type": "BOTH", "domain": "oddsserve.com"}, {"seller_id": "97", "name": "Axel Springer Teaser Ad GmbH (Non RTB)", "seller_type": "PUBLISHER", "domain": "adup-tech.de"}, {"seller_id": "11176729", "name": "IDM", "seller_type": "BOTH", "domain": "idmgroup.com"}, {"seller_id": "2329165", "name": "pilot (YDC)", "seller_type": "INTERMEDIARY", "domain": "pilot.de"}, {"seller_id": "9926502", "name": "Stream5 GmbH", "seller_type": "PUBLISHER", "domain": "autolina.ch"}, {"seller_id": "6332043", "name": "AdTech Factory GmbH & Co. KG", "seller_type": "BOTH", "domain": "bcn.burda.com"}, {"seller_id": "5179713", "name": "Aumago GmbH", "seller_type": "INTERMEDIARY", "domain": "aumago.com"}, {"seller_id": "5230265", "name": "meinestadt.de GmbH", "seller_type": "PUBLISHER", "domain": "meinestadt.de"}, {"seller_id": "8717", "name": "Axel Springer Teaser Ad GmbH", "seller_type": "BOTH", "domain": "adup-tech.com"}, {"seller_id": "5798882", "name": "Publicis (YDC)", "seller_type": "INTERMEDIARY", "domain": "publicispixelpark.de"}, {"seller_id": "5494672", "name": "Performance Advertising (YDC)", "seller_type": "INTERMEDIARY", "domain": "performance-advertising.de"}, {"seller_id": "11216419", "name": "madvertise media GmbH", "seller_type": "BOTH", "domain": "madvertise.com/de/"}, {"seller_id": "2376680", "name": "Lunar", "seller_type": "PUBLISHER", "domain": "lunar.de"}, {"seller_id": "2373635", "name": "ARB\u00d6", "seller_type": "PUBLISHER", "domain": "arboe.at"}, {"seller_id": "2348890", "name": "Yieldlab Manages Service", "seller_type": "PUBLISHER", "domain": "yieldlab.de"}, {"seller_id": "2448254", "name": "netdoktor.at GmbH", "seller_type": "PUBLISHER", "domain": "netdoktor.at"}, {"seller_id": "2510226", "name": "Aconmedia Ltd & Co. Kg", "seller_type": "PUBLISHER", "domain": "aconmedia.de"}, {"seller_id": "2448123", "name": "Glomex GmbH", "seller_type": "INTERMEDIARY", "domain": "glomex.com"}, {"seller_id": "2510891", "name": "AdDefend GmbH", "seller_type": "INTERMEDIARY", "domain": "addefend.com"}, {"seller_id": "6355352", "name": "Weischer Online GmbH", "seller_type": "PUBLISHER", "domain": "weischer.media.de"}, {"seller_id": "5494697", "name": "B\u00f6rseGo AG", "seller_type": "PUBLISHER", "domain": "godmode-trader.de"}, {"seller_id": "133612", "name": "VGN Medien Holding GmbH", "seller_type": "PUBLISHER", "domain": "vgn.at"}, {"seller_id": "6152554", "name": "MGA Intermedia GmbH", "seller_type": "BOTH", "domain": "mga-intermedia.com"}, {"seller_id": "6119459", "name": "Salzburger Nachrichten Verlagsgesellschaft m.b.H. & Co KG", "seller_type": "PUBLISHER", "domain": "sn.at"}, {"seller_id": "9293918", "name": "YLM Yieldlab AG", "seller_type": "PUBLISHER", "domain": "yieldlab.de"}, {"seller_id": "6248161", "name": "Video Intelligence AG", "seller_type": "INTERMEDIARY", "domain": "vi.ai"}, {"seller_id": "10356976", "name": "Zattoo Europa AG", "seller_type": "PUBLISHER", "domain": "zattoo.com"}, {"seller_id": "10723392", "name": "UZE Mobility", "seller_type": "PUBLISHER", "domain": "uze-mobility.comb"}, {"seller_id": "6374319", "name": "MSO Digital GmbH & Co. KG", "seller_type": "BOTH", "domain": "mso-digital.de"}, {"seller_id": "7069628", "name": "Hutchison Drei Austria GmbH", "seller_type": "PUBLISHER", "domain": "drei.at"}, {"seller_id": "6871963", "name": "Traffective GmbH", "seller_type": "INTERMEDIARY", "domain": "traffective.com"}, {"seller_id": "7525759", "name": "Sportradar Media Services GmbH", "seller_type": "PUBLISHER", "domain": "sportradar.com"}, {"seller_id": "706149", "name": "Quarter Media Technologies GmbH", "seller_type": "BOTH", "domain": "quartermedia.de"}, {"seller_id": "8464", "name": "Ad Alliance GmbH", "seller_type": "PUBLISHER", "domain": "ad-alliance.de"}, {"seller_id": "7568866", "name": "Visoon Video Impact GmbH & Co KG", "seller_type": "INTERMEDIARY", "domain": "visoon.de"}, {"seller_id": "7606521", "name": "MSO Digital GmbH & Co. KG - 2", "seller_type": "PUBLISHER", "domain": "mso-digital.de"}, {"seller_id": "8295301", "name": "HIMedia Deutschland AG", "seller_type": "PUBLISHER", "domain": "hi-media.de"}, {"seller_id": "8331826", "name": "Wimmer Medien GmbH & Co KG", "seller_type": "PUBLISHER", "domain": "nachrichten.at"}, {"seller_id": "10285198", "name": "SP- Snigel", "seller_type": "INTERMEDIARY", "domain": "snigel.com"}, {"seller_id": "8633311", "name": "Yieldlove GmbH", "seller_type": "BOTH", "domain": "yieldlove.de"}, {"seller_id": "12295565", "name": "ServusTV", "seller_type": "PUBLISHER", "domain": "servustv.com"}, {"seller_id": "9136676", "name": "Goldbach Germany", "seller_type": "PUBLISHER", "domain": "goldbach.com"}, {"seller_id": "8749863", "name": "ORF-Enterprise GmbH & Co KG", "seller_type": "PUBLISHER", "domain": "orf.at"}, {"seller_id": "8883126", "name": "RP Digital GmbH", "seller_type": "PUBLISHER", "domain": "rp-digital.de"}, {"seller_id": "8888896", "name": "AboutMedia Internetmarketing GmbH", "seller_type": "PUBLISHER", "domain": "aboutmedia.at"}, {"seller_id": "8369003", "name": "GWI Media Technologies GmbH", "seller_type": "PUBLISHER", "domain": "mtb-news.de"}, {"seller_id": "8889400", "name": "Omnicom Media Group GmbH Supply Account", "seller_type": "PUBLISHER", "domain": "omg.de"}, {"seller_id": "9716696", "name": "M,P,NEWMEDIA GmbH", "seller_type": "INTERMEDIARY", "domain": "mp-newmedia.com"}, {"seller_id": "9154098", "name": "WetterOnline", "seller_type": "PUBLISHER", "domain": "wetteronline.de"}, {"seller_id": "6374282", "name": "Omnicom Media Group Germany GmbH (YDC)", "seller_type": "INTERMEDIARY", "domain": "omnicommediagroup.de"}, {"seller_id": "2469221", "name": "adverserve digital advertising services GmbH", "seller_type": "PUBLISHER", "domain": "adverserve.at"}, {"seller_id": "9790691", "name": "Eat Smarter GmbH & Co KG", "seller_type": "PUBLISHER", "domain": "eatsmarter.de"}, {"seller_id": "9839017", "name": "Dentsu Aegis (YDC)", "seller_type": "INTERMEDIARY", "domain": "dentsu.com"}, {"seller_id": "6032692", "name": "onAd GmbH & Co. KG", "seller_type": "INTERMEDIARY", "domain": "onad.de"}, {"seller_id": "9935198", "name": "UIM YDC", "seller_type": "BOTH", "domain": "united-internet-media.de"}, {"seller_id": "830726", "name": "diva-e Advertising GmbH", "seller_type": "BOTH", "domain": "advertising.de"}, {"seller_id": "10215650", "name": "Wetter.com GmbH", "seller_type": "PUBLISHER", "domain": "wetter.com"}, {"seller_id": "10680789", "name": "FEIBRA GMBH", "seller_type": "PUBLISHER", "domain": "feibra.at"}, {"seller_id": "10702603", "name": "FUNKE Digital GmbH", "seller_type": "PUBLISHER", "domain": "funkedigital.de"}, {"seller_id": "10710236", "name": "TargetVideo GmbH", "seller_type": "BOTH", "domain": "target-video.com"}, {"seller_id": "81880", "name": "Mirando GmbH & Co. KG", "seller_type": "PUBLISHER", "domain": "mirando.de"}, {"seller_id": "21719", "name": "iq digital media marketing gmbh", "seller_type": "PUBLISHER", "domain": "iqdigital.de"}, {"seller_id": "513042", "name": "Geizhals - Preisvergleich Internet Services AG", "seller_type": "PUBLISHER", "domain": "geizhals.at"}, {"seller_id": "9946606", "name": "Welect", "seller_type": "INTERMEDIARY", "domain": "welect.de"}, {"seller_id": "172", "name": "SPIEGEL-Verlag Rudolf Augstein GmbH & Co. KG", "seller_type": "PUBLISHER", "domain": "spiegel.media"}, {"seller_id": "12376286", "name": "DuMont.next GmbH & Co. KG", "seller_type": "BOTH", "domain": "dumont.de"}, {"seller_id": "12459150", "name": "ZackZack.at", "seller_type": "PUBLISHER", "domain": "zackzack.at"}, {"seller_id": "12151798", "name": "Signa CRM Solutions GmbH", "seller_type": "PUBLISHER", "domain": "signa.at/de/"}, {"seller_id": "11302806", "name": "Factor Eleven", "seller_type": "INTERMEDIARY", "domain": "factor-eleven.de"}, {"seller_id": "9138435", "name": "Regionalmedien Austria AG", "seller_type": "PUBLISHER", "domain": "regionalmedien.at"}, {"seller_id": "11309970", "name": "IP \u00d6sterreich GmbH", "seller_type": "INTERMEDIARY", "domain": "ip.at"}, {"seller_id": "11492277", "name": "JCC", "seller_type": "INTERMEDIARY", "domain": "jcc.group"}, {"seller_id": "5103408", "name": "Digitalsunray Media", "seller_type": "PUBLISHER", "domain": "digitalsunray.com/"}, {"seller_id": "13784978", "name": "MPX YDC", "seller_type": "INTERMEDIARY", "domain": "mpx.de"}, {"seller_id": "12666727", "name": "\u00d6sterreichischer Wirtschaftsverlag GmbH", "seller_type": "PUBLISHER", "domain": "wirtschaftsverlag.at"}]}